{"metadata": {"dataVersion": "2", "matchId": "BR1_2994792779", "participants": ["GixBtZ_o5Cny7uYaME5kb9g4muI4sXt_ofN7IPIOicUqqNllmavEa93BbRVIuCv8TFQcrLIleFwjlQ", "egHrgVCWh9IzU_BohYaMMPVx1rxcJ3ST-afHdXMSBkMNUO--gFfph7lvwZgw2VlzK4WMnjoq-y7dSA", "zFbPVkoDimGDsC_BI31ywtoygydTcI92m-7H3vw7wLVIUHs1xEj377VIl-cm1bOev0ZpuhyO1n2huA", "DP5AKk9T-2cXz-xyuelSuyjjelMbDnD7_SmCRSf0TCYzHl6lXbrYFrBli6bis3iwk7Amv3LSQ6hnLg", "RUSb5mH-h0PAMtE8AeZZGL-bKlR8Y12e0PkTiMSpP33UrA79YVX9yJW-tZdmneMPz23Xb29r07ObHg", "Oc3S3CKFvtVarGXpMUZbH7fXxr4lwkJsLUCtdmkWYLUSi89BRqPJAfWkLVC4iAJpMm9f1Tu71evQ5g", "HBkiEhOdgIONz6vvH24dcoDj7Inncl_6DEqqeo_zCrcdI1Suhtwdmji02YoI9ut7qC4wiRHQ9iGQ9w", "y_jizTOkVdva02Q545jf0onoHKHdcXiQ1u3GjMtlRGag6foBj7paNPCqF9Iu7ZTwCt6m0mEyVmRwdA", "rDib1FSxplhn5DSdcgixAI39obnCHkf85klzk5Nyakk0nrG7QxfhtB9ZkRy00vNby7k1gSeN8sXfqw", "jMs2_SjqNWHe9uAp-hfp541qqXOmeYNQ5khxyOqT_PPmRmveXvtl7miQKwX90ZYl5ZE9jPb-mspBrA"]}, "info": {"endOfGameResult": "GameComplete", "gameCreation": 1725646042192, "gameDuration": 1722, "gameEndTimestamp": 1725647928260, "gameId": 2994792779, "gameMode": "CLASSIC", "gameName": "teambuilder-match-2994792779", "gameStartTimestamp": 1725646205928, "gameType": "MATCHED_GAME", "gameVersion": "14.17.615.2328", "mapId": 11, "participants": [{"allInPings": 0, "assistMePings": 0, "assists": 1, "baronKills": 0, "basicPings": 0, "bountyLevel": 0, "challenges": {"12AssistStreakCount": 0, "InfernalScalePickup": 28, "SWARM_DefeatAatrox": 0, "SWARM_DefeatBriar": 0, "SWARM_DefeatMiniBosses": 0, "SWARM_EvolveWeapon": 0, "SWARM_Have3Passives": 0, "SWARM_KillEnemy": 0, "SWARM_PickupGold": 0, "SWARM_ReachLevel50": 0, "SWARM_Survive15Min": 0, "SWARM_WinWith5EvolvedWeapons": 0, "abilityUses": 92, "acesBefore15Minutes": 0, "alliedJungleMonsterKills": 0, "baronTakedowns": 0, "blastConeOppositeOpponentCount": 0, "bountyGold": 150, "buffsStolen": 0, "completeSupportQuestInTime": 0, "controlWardTimeCoverageInRiverOrEnemyHalf": 0.7887822445998376, "controlWardsPlaced": 1, "damagePerMinute": 529.8005424698237, "damageTakenOnTeamPercentage": 0.2857379178737102, "dancedWithRiftHerald": 0, "deathsByEnemyChamps": 5, "dodgeSkillShotsSmallWindow": 32, "doubleAces": 0, "dragonTakedowns": 0, "earlyLaningPhaseGoldExpAdvantage": 0, "effectiveHealAndShielding": 0, "elderDragonKillsWithOpposingSoul": 0, "elderDragonMultikills": 0, "enemyChampionImmobilizations": 35, "enemyJungleMonsterKills": 0, "epicMonsterKillsNearEnemyJungler": 0, "epicMonsterKillsWithin30SecondsOfSpawn": 0, "epicMonsterSteals": 0, "epicMonsterStolenWithoutSmite": 0, "firstTurretKilled": 0, "fistBumpParticipation": 0, "flawlessAces": 0, "fullTeamTakedown": 0, "gameLength": 1722.634910681, "getTakedownsInAllLanesEarlyJungleAsLaner": 0, "goldPerMinute": 292.53746733080663, "hadAfkTeammate": 1, "hadOpenNexus": 0, "immobilizeAndKillWithAlly": 3, "initialBuffCount": 0, "initialCrabCount": 0, "jungleCsBefore10Minutes": 0, "junglerTakedownsNearDamagedEpicMonster": 1, "kTurretsDestroyedBeforePlatesFall": 0, "kda": 1, "killAfterHiddenWithAlly": 0, "killParticipation": 0.29411764705882354, "killedChampTookFullTeamDamageSurvived": 0, "killingSprees": 0, "killsNearEnemyTurret": 1, "killsOnOtherLanesEarlyJungleAsLaner": 0, "killsOnRecentlyHealedByAramPack": 0, "killsUnderOwnTurret": 2, "killsWithHelpFromEpicMonster": 0, "knockEnemyIntoTeamAndKill": 0, "landSkillShotsEarlyGame": 0, "laneMinionsFirst10Minutes": 51, "laningPhaseGoldExpAdvantage": 0, "legendaryCount": 0, "legendaryItemUsed": [3091, 3065], "lostAnInhibitor": 0, "maxCsAdvantageOnLaneOpponent": 16, "maxKillDeficit": 0, "maxLevelLeadLaneOpponent": 1, "mejaisFullStackInTime": 0, "moreEnemyJungleThanOpponent": 0, "multiKillOneSpell": 0, "multiTurretRiftHeraldCount": 0, "multikills": 0, "multikillsAfterAggressiveFlash": 0, "outerTurretExecutesBefore10Minutes": 0, "outnumberedKills": 0, "outnumberedNexusKill": 0, "perfectDragonSoulsTaken": 0, "perfectGame": 0, "pickKillWithAlly": 2, "playedChampSelectPosition": 1, "poroExplosions": 0, "quickCleanse": 0, "quickFirstTurret": 0, "quickSoloKills": 0, "riftHeraldTakedowns": 0, "saveAllyFromDeath": 0, "scuttleCrabKills": 0, "skillshotsDodged": 193, "skillshotsHit": 0, "snowballsHit": 0, "soloBaronKills": 0, "soloKills": 2, "stealthWardsPlaced": 6, "survivedSingleDigitHpCount": 0, "survivedThreeImmobilizesInFight": 8, "takedownOnFirstTurret": 0, "takedowns": 5, "takedownsAfterGainingLevelAdvantage": 0, "takedownsBeforeJungleMinionSpawn": 0, "takedownsFirstXMinutes": 4, "takedownsInAlcove": 0, "takedownsInEnemyFountain": 0, "teamBaronKills": 0, "teamDamagePercentage": 0.19734918879886706, "teamElderDragonKills": 0, "teamRiftHeraldKills": 0, "tookLargeDamageSurvived": 1, "turretPlatesTaken": 0, "turretTakedowns": 0, "turretsTakenWithRiftHerald": 0, "twentyMinionsIn3SecondsCount": 0, "twoWardsOneSweeperCount": 0, "unseenRecalls": 0, "visionScoreAdvantageLaneOpponent": 0.03156280517578125, "visionScorePerMinute": 0.5461161599167371, "voidMonsterKill": 0, "wardTakedowns": 0, "wardTakedownsBefore20M": 0, "wardsGuarded": 0}, "champExperience": 11114, "champLevel": 13, "championId": 19, "championName": "Warwick", "championTransform": 0, "commandPings": 0, "consumablesPurchased": 2, "damageDealtToBuildings": 630, "damageDealtToObjectives": 630, "damageDealtToTurrets": 630, "damageSelfMitigated": 43048, "dangerPings": 0, "deaths": 5, "detectorWardsPlaced": 1, "doubleKills": 0, "dragonKills": 0, "eligibleForProgression": true, "enemyMissingPings": 0, "enemyVisionPings": 1, "firstBloodAssist": false, "firstBloodKill": false, "firstTowerAssist": false, "firstTowerKill": false, "gameEndedInEarlySurrender": false, "gameEndedInSurrender": false, "getBackPings": 0, "goldEarned": 8398, "goldSpent": 8225, "holdPings": 0, "individualPosition": "TOP", "inhibitorKills": 0, "inhibitorTakedowns": 0, "inhibitorsLost": 3, "item0": 1054, "item1": 3111, "item2": 3091, "item3": 3065, "item4": 1033, "item5": 1036, "item6": 3363, "itemsPurchased": 20, "killingSprees": 1, "kills": 4, "lane": "TOP", "largestCriticalStrike": 0, "largestKillingSpree": 2, "largestMultiKill": 1, "longestTimeSpentLiving": 484, "magicDamageDealt": 32423, "magicDamageDealtToChampions": 10823, "magicDamageTaken": 26260, "missions": {"playerScore0": 0, "playerScore1": 0, "playerScore2": 0, "playerScore3": 0, "playerScore4": 0, "playerScore5": 0, "playerScore6": 0, "playerScore7": 0, "playerScore8": 0, "playerScore9": 0, "playerScore10": 0, "playerScore11": 0}, "needVisionPings": 0, "neutralMinionsKilled": 0, "nexusKills": 0, "nexusLost": 1, "nexusTakedowns": 0, "objectivesStolen": 0, "objectivesStolenAssists": 0, "onMyWayPings": 0, "participantId": 1, "pentaKills": 0, "perks": {"statPerks": {"defense": 5001, "flex": 5008, "offense": 5005}, "styles": [{"description": "primaryStyle", "selections": [{"perk": 8437, "var1": 966, "var2": 648, "var3": 0}, {"perk": 8446, "var1": 496, "var2": 0, "var3": 0}, {"perk": 8444, "var1": 2411, "var2": 0, "var3": 0}, {"perk": 8453, "var1": 2162, "var2": 434, "var3": 0}], "style": 8400}, {"description": "subStyle", "selections": [{"perk": 8299, "var1": 991, "var2": 0, "var3": 0}, {"perk": 8009, "var1": 1063, "var2": 0, "var3": 0}], "style": 8000}]}, "physicalDamageDealt": 33465, "physicalDamageDealtToChampions": 3827, "physicalDamageTaken": 11623, "placement": 0, "playerAugment1": 0, "playerAugment2": 0, "playerAugment3": 0, "playerAugment4": 0, "playerAugment5": 0, "playerAugment6": 0, "playerSubteamId": 0, "profileIcon": 5642, "pushPings": 0, "puuid": "GixBtZ_o5Cny7uYaME5kb9g4muI4sXt_ofN7IPIOicUqqNllmavEa93BbRVIuCv8TFQcrLIleFwjlQ", "quadraKills": 0, "riotIdGameName": "ZCometa", "riotIdTagline": "gab", "role": "SOLO", "sightWardsBoughtInGame": 0, "spell1Casts": 56, "spell2Casts": 4, "spell3Casts": 23, "spell4Casts": 9, "subteamPlacement": 0, "summoner1Casts": 7, "summoner1Id": 21, "summoner2Casts": 4, "summoner2Id": 4, "summonerId": "X-LiamrYMtg9rcFtlFINTvRti1lGPzhw7ap1e_WXemxc-LI0CSR166kx4g", "summonerLevel": 470, "summonerName": "ZCometa", "teamEarlySurrendered": false, "teamId": 100, "teamPosition": "TOP", "timeCCingOthers": 27, "timePlayed": 1722, "totalAllyJungleMinionsKilled": 0, "totalDamageDealt": 78932, "totalDamageDealtToChampions": 15210, "totalDamageShieldedOnTeammates": 0, "totalDamageTaken": 39478, "totalEnemyJungleMinionsKilled": 0, "totalHeal": 15902, "totalHealsOnTeammates": 0, "totalMinionsKilled": 126, "totalTimeCCDealt": 129, "totalTimeSpentDead": 164, "totalUnitsHealed": 1, "tripleKills": 0, "trueDamageDealt": 13043, "trueDamageDealtToChampions": 560, "trueDamageTaken": 1594, "turretKills": 0, "turretTakedowns": 0, "turretsLost": 11, "unrealKills": 0, "visionClearedPings": 0, "visionScore": 15, "visionWardsBoughtInGame": 1, "wardsKilled": 0, "wardsPlaced": 10, "win": false}, {"allInPings": 0, "assistMePings": 5, "assists": 3, "baronKills": 0, "basicPings": 0, "bountyLevel": 0, "challenges": {"12AssistStreakCount": 0, "InfernalScalePickup": 20, "SWARM_DefeatAatrox": 0, "SWARM_DefeatBriar": 0, "SWARM_DefeatMiniBosses": 0, "SWARM_EvolveWeapon": 0, "SWARM_Have3Passives": 0, "SWARM_KillEnemy": 0, "SWARM_PickupGold": 0, "SWARM_ReachLevel50": 0, "SWARM_Survive15Min": 0, "SWARM_WinWith5EvolvedWeapons": 0, "abilityUses": 186, "acesBefore15Minutes": 0, "alliedJungleMonsterKills": 59, "baronTakedowns": 0, "blastConeOppositeOpponentCount": 0, "bountyGold": 500, "buffsStolen": 0, "completeSupportQuestInTime": 0, "controlWardsPlaced": 1, "damagePerMinute": 604.9575619090548, "damageTakenOnTeamPercentage": 0.24959805739852875, "dancedWithRiftHerald": 0, "deathsByEnemyChamps": 12, "dodgeSkillShotsSmallWindow": 34, "doubleAces": 0, "dragonTakedowns": 0, "earlyLaningPhaseGoldExpAdvantage": 0, "effectiveHealAndShielding": 0, "elderDragonKillsWithOpposingSoul": 0, "elderDragonMultikills": 0, "enemyChampionImmobilizations": 58, "enemyJungleMonsterKills": 0, "epicMonsterKillsNearEnemyJungler": 0, "epicMonsterKillsWithin30SecondsOfSpawn": 0, "epicMonsterSteals": 0, "epicMonsterStolenWithoutSmite": 0, "firstTurretKilled": 0, "fistBumpParticipation": 0, "flawlessAces": 0, "fullTeamTakedown": 0, "gameLength": 1722.634910681, "goldPerMinute": 311.2561005674932, "hadAfkTeammate": 1, "hadOpenNexus": 0, "immobilizeAndKillWithAlly": 4, "initialBuffCount": 2, "initialCrabCount": 0, "jungleCsBefore10Minutes": 45.60000005364418, "junglerKillsEarlyJungle": 0, "junglerTakedownsNearDamagedEpicMonster": 1, "kTurretsDestroyedBeforePlatesFall": 0, "kda": 0.5, "killAfterHiddenWithAlly": 1, "killParticipation": 0.35294117647058826, "killedChampTookFullTeamDamageSurvived": 0, "killingSprees": 0, "killsNearEnemyTurret": 0, "killsOnLanersEarlyJungleAsJungler": 0, "killsOnRecentlyHealedByAramPack": 0, "killsUnderOwnTurret": 0, "killsWithHelpFromEpicMonster": 0, "knockEnemyIntoTeamAndKill": 0, "landSkillShotsEarlyGame": 3, "laneMinionsFirst10Minutes": 3, "laningPhaseGoldExpAdvantage": 0, "legendaryCount": 0, "legendaryItemUsed": [6692, 3091], "lostAnInhibitor": 0, "maxCsAdvantageOnLaneOpponent": 2.9802322387695312e-08, "maxKillDeficit": 0, "maxLevelLeadLaneOpponent": 0, "mejaisFullStackInTime": 0, "moreEnemyJungleThanOpponent": -38.500000059604645, "multiKillOneSpell": 0, "multiTurretRiftHeraldCount": 0, "multikills": 0, "multikillsAfterAggressiveFlash": 0, "outerTurretExecutesBefore10Minutes": 0, "outnumberedKills": 2, "outnumberedNexusKill": 0, "perfectDragonSoulsTaken": 0, "perfectGame": 0, "pickKillWithAlly": 6, "playedChampSelectPosition": 1, "poroExplosions": 0, "quickCleanse": 0, "quickFirstTurret": 0, "quickSoloKills": 0, "riftHeraldTakedowns": 0, "saveAllyFromDeath": 0, "scuttleCrabKills": 1, "skillshotsDodged": 205, "skillshotsHit": 19, "snowballsHit": 0, "soloBaronKills": 0, "soloKills": 0, "stealthWardsPlaced": 7, "survivedSingleDigitHpCount": 0, "survivedThreeImmobilizesInFight": 2, "takedownOnFirstTurret": 0, "takedowns": 6, "takedownsAfterGainingLevelAdvantage": 0, "takedownsBeforeJungleMinionSpawn": 0, "takedownsFirstXMinutes": 3, "takedownsInAlcove": 0, "takedownsInEnemyFountain": 0, "teamBaronKills": 0, "teamDamagePercentage": 0.22534496386872319, "teamElderDragonKills": 0, "teamRiftHeraldKills": 0, "tookLargeDamageSurvived": 0, "turretPlatesTaken": 0, "turretTakedowns": 1, "turretsTakenWithRiftHerald": 0, "twentyMinionsIn3SecondsCount": 0, "twoWardsOneSweeperCount": 0, "unseenRecalls": 0, "visionScoreAdvantageLaneOpponent": -0.4588596224784851, "visionScorePerMinute": 0.6014061929804235, "voidMonsterKill": 0, "wardTakedowns": 1, "wardTakedownsBefore20M": 0, "wardsGuarded": 1}, "champExperience": 9836, "champLevel": 12, "championId": 233, "championName": "Briar", "championTransform": 0, "commandPings": 12, "consumablesPurchased": 2, "damageDealtToBuildings": 1732, "damageDealtToObjectives": 2746, "damageDealtToTurrets": 1732, "damageSelfMitigated": 32289, "dangerPings": 0, "deaths": 12, "detectorWardsPlaced": 1, "doubleKills": 0, "dragonKills": 0, "eligibleForProgression": true, "enemyMissingPings": 2, "enemyVisionPings": 0, "firstBloodAssist": false, "firstBloodKill": false, "firstTowerAssist": false, "firstTowerKill": false, "gameEndedInEarlySurrender": false, "gameEndedInSurrender": false, "getBackPings": 0, "goldEarned": 8936, "goldSpent": 8325, "holdPings": 0, "individualPosition": "JUNGLE", "inhibitorKills": 0, "inhibitorTakedowns": 0, "inhibitorsLost": 3, "item0": 2022, "item1": 3091, "item2": 3111, "item3": 6692, "item4": 1028, "item5": 1006, "item6": 3363, "itemsPurchased": 20, "killingSprees": 1, "kills": 3, "lane": "JUNGLE", "largestCriticalStrike": 0, "largestKillingSpree": 2, "largestMultiKill": 1, "longestTimeSpentLiving": 342, "magicDamageDealt": 15023, "magicDamageDealtToChampions": 5225, "magicDamageTaken": 18456, "missions": {"playerScore0": 0, "playerScore1": 0, "playerScore2": 0, "playerScore3": 0, "playerScore4": 0, "playerScore5": 0, "playerScore6": 0, "playerScore7": 0, "playerScore8": 0, "playerScore9": 0, "playerScore10": 0, "playerScore11": 0}, "needVisionPings": 1, "neutralMinionsKilled": 95, "nexusKills": 0, "nexusLost": 1, "nexusTakedowns": 0, "objectivesStolen": 0, "objectivesStolenAssists": 0, "onMyWayPings": 10, "participantId": 2, "pentaKills": 0, "perks": {"statPerks": {"defense": 5001, "flex": 5008, "offense": 5005}, "styles": [{"description": "primaryStyle", "selections": [{"perk": 8010, "var1": 227, "var2": 0, "var3": 0}, {"perk": 9111, "var1": 381, "var2": 120, "var3": 0}, {"perk": 9104, "var1": 17, "var2": 50, "var3": 0}, {"perk": 8014, "var1": 353, "var2": 0, "var3": 0}], "style": 8000}, {"description": "subStyle", "selections": [{"perk": 8429, "var1": 58, "var2": 10, "var3": 12}, {"perk": 8451, "var1": 146, "var2": 0, "var3": 0}], "style": 8400}]}, "physicalDamageDealt": 92368, "physicalDamageDealtToChampions": 11265, "physicalDamageTaken": 14949, "placement": 0, "playerAugment1": 0, "playerAugment2": 0, "playerAugment3": 0, "playerAugment4": 0, "playerAugment5": 0, "playerAugment6": 0, "playerSubteamId": 0, "profileIcon": 5974, "pushPings": 0, "puuid": "egHrgVCWh9IzU_BohYaMMPVx1rxcJ3ST-afHdXMSBkMNUO--gFfph7lvwZgw2VlzK4WMnjoq-y7dSA", "quadraKills": 0, "riotIdGameName": "blackTood", "riotIdTagline": "JGDIF", "role": "NONE", "sightWardsBoughtInGame": 0, "spell1Casts": 42, "spell2Casts": 110, "spell3Casts": 28, "spell4Casts": 6, "subteamPlacement": 0, "summoner1Casts": 4, "summoner1Id": 4, "summoner2Casts": 12, "summoner2Id": 11, "summonerId": "JzaYGRTlEvVfnpjo4jBbkQfAnu-O9IOFi_TjFpV9JopgRQ", "summonerLevel": 651, "summonerName": "blackTood", "teamEarlySurrendered": false, "teamId": 100, "teamPosition": "JUNGLE", "timeCCingOthers": 40, "timePlayed": 1722, "totalAllyJungleMinionsKilled": 85, "totalDamageDealt": 140549, "totalDamageDealtToChampions": 17368, "totalDamageShieldedOnTeammates": 0, "totalDamageTaken": 34484, "totalEnemyJungleMinionsKilled": 0, "totalHeal": 21476, "totalHealsOnTeammates": 0, "totalMinionsKilled": 23, "totalTimeCCDealt": 268, "totalTimeSpentDead": 282, "totalUnitsHealed": 1, "tripleKills": 0, "trueDamageDealt": 33156, "trueDamageDealtToChampions": 878, "trueDamageTaken": 1078, "turretKills": 1, "turretTakedowns": 1, "turretsLost": 11, "unrealKills": 0, "visionClearedPings": 0, "visionScore": 17, "visionWardsBoughtInGame": 1, "wardsKilled": 1, "wardsPlaced": 10, "win": false}, {"allInPings": 0, "assistMePings": 2, "assists": 2, "baronKills": 0, "basicPings": 0, "bountyLevel": 0, "challenges": {"12AssistStreakCount": 0, "InfernalScalePickup": 17, "SWARM_DefeatAatrox": 0, "SWARM_DefeatBriar": 0, "SWARM_DefeatMiniBosses": 0, "SWARM_EvolveWeapon": 0, "SWARM_Have3Passives": 0, "SWARM_KillEnemy": 0, "SWARM_PickupGold": 0, "SWARM_ReachLevel50": 0, "SWARM_Survive15Min": 0, "SWARM_WinWith5EvolvedWeapons": 0, "abilityUses": 334, "acesBefore15Minutes": 0, "alliedJungleMonsterKills": 0, "baronTakedowns": 0, "blastConeOppositeOpponentCount": 0, "bountyGold": 675, "buffsStolen": 0, "completeSupportQuestInTime": 0, "controlWardsPlaced": 0, "damagePerMinute": 590.4445249866714, "damageTakenOnTeamPercentage": 0.1344806954742165, "dancedWithRiftHerald": 0, "deathsByEnemyChamps": 9, "dodgeSkillShotsSmallWindow": 15, "doubleAces": 0, "dragonTakedowns": 0, "earlyLaningPhaseGoldExpAdvantage": 0, "effectiveHealAndShielding": 0, "elderDragonKillsWithOpposingSoul": 0, "elderDragonMultikills": 0, "enemyChampionImmobilizations": 57, "enemyJungleMonsterKills": 0, "epicMonsterKillsNearEnemyJungler": 0, "epicMonsterKillsWithin30SecondsOfSpawn": 0, "epicMonsterSteals": 0, "epicMonsterStolenWithoutSmite": 0, "firstTurretKilled": 0, "fistBumpParticipation": 0, "flawlessAces": 0, "fullTeamTakedown": 0, "gameLength": 1722.634910681, "getTakedownsInAllLanesEarlyJungleAsLaner": 0, "goldPerMinute": 351.76663640335545, "hadAfkTeammate": 1, "hadOpenNexus": 0, "immobilizeAndKillWithAlly": 3, "initialBuffCount": 0, "initialCrabCount": 0, "jungleCsBefore10Minutes": 0, "junglerTakedownsNearDamagedEpicMonster": 0, "kTurretsDestroyedBeforePlatesFall": 0, "kda": 0.7777777777777778, "killAfterHiddenWithAlly": 1, "killParticipation": 0.4117647058823529, "killedChampTookFullTeamDamageSurvived": 0, "killingSprees": 0, "killsNearEnemyTurret": 1, "killsOnOtherLanesEarlyJungleAsLaner": 0, "killsOnRecentlyHealedByAramPack": 0, "killsUnderOwnTurret": 3, "killsWithHelpFromEpicMonster": 0, "knockEnemyIntoTeamAndKill": 5, "landSkillShotsEarlyGame": 3, "laneMinionsFirst10Minutes": 60, "laningPhaseGoldExpAdvantage": 0, "legendaryCount": 0, "legendaryItemUsed": [6655, 3157], "lostAnInhibitor": 0, "maxCsAdvantageOnLaneOpponent": 16, "maxKillDeficit": 0, "maxLevelLeadLaneOpponent": 1, "mejaisFullStackInTime": 0, "moreEnemyJungleThanOpponent": 0, "multiKillOneSpell": 0, "multiTurretRiftHeraldCount": 0, "multikills": 0, "multikillsAfterAggressiveFlash": 0, "outerTurretExecutesBefore10Minutes": 0, "outnumberedKills": 0, "outnumberedNexusKill": 0, "perfectDragonSoulsTaken": 0, "perfectGame": 0, "pickKillWithAlly": 4, "playedChampSelectPosition": 1, "poroExplosions": 0, "quickCleanse": 0, "quickFirstTurret": 0, "quickSoloKills": 0, "riftHeraldTakedowns": 0, "saveAllyFromDeath": 0, "scuttleCrabKills": 0, "skillshotsDodged": 117, "skillshotsHit": 55, "snowballsHit": 0, "soloBaronKills": 0, "soloKills": 2, "stealthWardsPlaced": 10, "survivedSingleDigitHpCount": 0, "survivedThreeImmobilizesInFight": 0, "takedownOnFirstTurret": 0, "takedowns": 7, "takedownsAfterGainingLevelAdvantage": 0, "takedownsBeforeJungleMinionSpawn": 0, "takedownsFirstXMinutes": 2, "takedownsInAlcove": 0, "takedownsInEnemyFountain": 0, "teamBaronKills": 0, "teamDamagePercentage": 0.21993889906877348, "teamElderDragonKills": 0, "teamRiftHeraldKills": 0, "tookLargeDamageSurvived": 0, "turretPlatesTaken": 0, "turretTakedowns": 0, "turretsTakenWithRiftHerald": 0, "twentyMinionsIn3SecondsCount": 0, "twoWardsOneSweeperCount": 0, "unseenRecalls": 0, "visionScoreAdvantageLaneOpponent": -0.33740508556365967, "visionScorePerMinute": 0.7572742749365301, "voidMonsterKill": 0, "wardTakedowns": 3, "wardTakedownsBefore20M": 3, "wardsGuarded": 0}, "champExperience": 12771, "champLevel": 14, "championId": 134, "championName": "Syndra", "championTransform": 0, "commandPings": 11, "consumablesPurchased": 4, "damageDealtToBuildings": 0, "damageDealtToObjectives": 0, "damageDealtToTurrets": 0, "damageSelfMitigated": 6495, "dangerPings": 0, "deaths": 9, "detectorWardsPlaced": 0, "doubleKills": 0, "dragonKills": 0, "eligibleForProgression": true, "enemyMissingPings": 20, "enemyVisionPings": 7, "firstBloodAssist": false, "firstBloodKill": false, "firstTowerAssist": false, "firstTowerKill": false, "gameEndedInEarlySurrender": false, "gameEndedInSurrender": false, "getBackPings": 1, "goldEarned": 10099, "goldSpent": 9500, "holdPings": 0, "individualPosition": "MIDDLE", "inhibitorKills": 0, "inhibitorTakedowns": 0, "inhibitorsLost": 3, "item0": 1056, "item1": 6655, "item2": 3020, "item3": 3157, "item4": 4630, "item5": 1026, "item6": 3340, "itemsPurchased": 19, "killingSprees": 1, "kills": 5, "lane": "MIDDLE", "largestCriticalStrike": 0, "largestKillingSpree": 2, "largestMultiKill": 1, "longestTimeSpentLiving": 305, "magicDamageDealt": 104131, "magicDamageDealtToChampions": 14681, "magicDamageTaken": 14698, "missions": {"playerScore0": 0, "playerScore1": 0, "playerScore2": 0, "playerScore3": 0, "playerScore4": 0, "playerScore5": 0, "playerScore6": 0, "playerScore7": 0, "playerScore8": 0, "playerScore9": 0, "playerScore10": 0, "playerScore11": 0}, "needVisionPings": 0, "neutralMinionsKilled": 0, "nexusKills": 0, "nexusLost": 1, "nexusTakedowns": 0, "objectivesStolen": 0, "objectivesStolenAssists": 0, "onMyWayPings": 17, "participantId": 3, "pentaKills": 0, "perks": {"statPerks": {"defense": 5001, "flex": 5008, "offense": 5005}, "styles": [{"description": "primaryStyle", "selections": [{"perk": 8369, "var1": 729, "var2": 435, "var3": 0}, {"perk": 8304, "var1": 12, "var2": 0, "var3": 0}, {"perk": 8345, "var1": 3, "var2": 0, "var3": 0}, {"perk": 8347, "var1": 0, "var2": 0, "var3": 0}], "style": 8300}, {"description": "subStyle", "selections": [{"perk": 8226, "var1": 250, "var2": 540, "var3": 0}, {"perk": 8210, "var1": 16, "var2": 0, "var3": 0}], "style": 8200}]}, "physicalDamageDealt": 6763, "physicalDamageDealtToChampions": 583, "physicalDamageTaken": 3353, "placement": 0, "playerAugment1": 0, "playerAugment2": 0, "playerAugment3": 0, "playerAugment4": 0, "playerAugment5": 0, "playerAugment6": 0, "playerSubteamId": 0, "profileIcon": 5538, "pushPings": 1, "puuid": "zFbPVkoDimGDsC_BI31ywtoygydTcI92m-7H3vw7wLVIUHs1xEj377VIl-cm1bOev0ZpuhyO1n2huA", "quadraKills": 0, "riotIdGameName": "Satanica", "riotIdTagline": "goth", "role": "SOLO", "sightWardsBoughtInGame": 0, "spell1Casts": 128, "spell2Casts": 160, "spell3Casts": 39, "spell4Casts": 7, "subteamPlacement": 0, "summoner1Casts": 5, "summoner1Id": 4, "summoner2Casts": 2, "summoner2Id": 12, "summonerId": "xdG8XR5al3sSXlExyofEF_jE6OG4lmrxhBRquEw3JzBb5kBZ28IhZ5iFyw", "summonerLevel": 472, "summonerName": "ruiva do tchan", "teamEarlySurrendered": false, "teamId": 100, "teamPosition": "MIDDLE", "timeCCingOthers": 24, "timePlayed": 1722, "totalAllyJungleMinionsKilled": 0, "totalDamageDealt": 114274, "totalDamageDealtToChampions": 16952, "totalDamageShieldedOnTeammates": 0, "totalDamageTaken": 18580, "totalEnemyJungleMinionsKilled": 0, "totalHeal": 176, "totalHealsOnTeammates": 0, "totalMinionsKilled": 172, "totalTimeCCDealt": 388, "totalTimeSpentDead": 254, "totalUnitsHealed": 1, "tripleKills": 0, "trueDamageDealt": 3379, "trueDamageDealtToChampions": 1686, "trueDamageTaken": 528, "turretKills": 0, "turretTakedowns": 0, "turretsLost": 11, "unrealKills": 0, "visionClearedPings": 0, "visionScore": 21, "visionWardsBoughtInGame": 0, "wardsKilled": 3, "wardsPlaced": 10, "win": false}, {"allInPings": 1, "assistMePings": 13, "assists": 6, "baronKills": 0, "basicPings": 0, "bountyLevel": 0, "challenges": {"12AssistStreakCount": 0, "InfernalScalePickup": 17, "SWARM_DefeatAatrox": 0, "SWARM_DefeatBriar": 0, "SWARM_DefeatMiniBosses": 0, "SWARM_EvolveWeapon": 0, "SWARM_Have3Passives": 0, "SWARM_KillEnemy": 0, "SWARM_PickupGold": 0, "SWARM_ReachLevel50": 0, "SWARM_Survive15Min": 0, "SWARM_WinWith5EvolvedWeapons": 0, "abilityUses": 153, "acesBefore15Minutes": 0, "alliedJungleMonsterKills": 0, "baronTakedowns": 0, "blastConeOppositeOpponentCount": 0, "bountyGold": 0, "buffsStolen": 0, "completeSupportQuestInTime": 0, "controlWardsPlaced": 0, "damagePerMinute": 650.9439819036915, "damageTakenOnTeamPercentage": 0.13910127539908845, "dancedWithRiftHerald": 0, "deathsByEnemyChamps": 4, "dodgeSkillShotsSmallWindow": 11, "doubleAces": 0, "dragonTakedowns": 0, "earlyLaningPhaseGoldExpAdvantage": 0, "effectiveHealAndShielding": 0, "elderDragonKillsWithOpposingSoul": 0, "elderDragonMultikills": 0, "enemyChampionImmobilizations": 13, "enemyJungleMonsterKills": 0, "epicMonsterKillsNearEnemyJungler": 0, "epicMonsterKillsWithin30SecondsOfSpawn": 0, "epicMonsterSteals": 0, "epicMonsterStolenWithoutSmite": 0, "firstTurretKilled": 0, "fistBumpParticipation": 0, "flawlessAces": 0, "fullTeamTakedown": 0, "gameLength": 1722.634910681, "getTakedownsInAllLanesEarlyJungleAsLaner": 0, "goldPerMinute": 358.56893155080354, "hadAfkTeammate": 1, "hadOpenNexus": 0, "immobilizeAndKillWithAlly": 2, "initialBuffCount": 0, "initialCrabCount": 0, "jungleCsBefore10Minutes": 0, "junglerTakedownsNearDamagedEpicMonster": 0, "kTurretsDestroyedBeforePlatesFall": 0, "kda": 2, "killAfterHiddenWithAlly": 1, "killParticipation": 0.47058823529411764, "killedChampTookFullTeamDamageSurvived": 0, "killingSprees": 0, "killsNearEnemyTurret": 0, "killsOnOtherLanesEarlyJungleAsLaner": 0, "killsOnRecentlyHealedByAramPack": 0, "killsUnderOwnTurret": 2, "killsWithHelpFromEpicMonster": 0, "knockEnemyIntoTeamAndKill": 0, "landSkillShotsEarlyGame": 0, "laneMinionsFirst10Minutes": 61, "laningPhaseGoldExpAdvantage": 0, "legendaryCount": 0, "legendaryItemUsed": [3087, 3031], "lostAnInhibitor": 0, "maxCsAdvantageOnLaneOpponent": 22, "maxKillDeficit": 0, "maxLevelLeadLaneOpponent": 1, "mejaisFullStackInTime": 0, "moreEnemyJungleThanOpponent": 0, "multiKillOneSpell": 0, "multiTurretRiftHeraldCount": 0, "multikills": 0, "multikillsAfterAggressiveFlash": 0, "outerTurretExecutesBefore10Minutes": 0, "outnumberedKills": 0, "outnumberedNexusKill": 0, "perfectDragonSoulsTaken": 0, "perfectGame": 0, "pickKillWithAlly": 6, "playedChampSelectPosition": 1, "poroExplosions": 0, "quickCleanse": 0, "quickFirstTurret": 0, "quickSoloKills": 0, "riftHeraldTakedowns": 0, "saveAllyFromDeath": 0, "scuttleCrabKills": 0, "skillshotsDodged": 86, "skillshotsHit": 12, "snowballsHit": 0, "soloBaronKills": 0, "soloKills": 2, "stealthWardsPlaced": 8, "survivedSingleDigitHpCount": 0, "survivedThreeImmobilizesInFight": 0, "takedownOnFirstTurret": 0, "takedowns": 8, "takedownsAfterGainingLevelAdvantage": 0, "takedownsBeforeJungleMinionSpawn": 0, "takedownsFirstXMinutes": 3, "takedownsInAlcove": 0, "takedownsInEnemyFountain": 0, "teamBaronKills": 0, "teamDamagePercentage": 0.24247477396555311, "teamElderDragonKills": 0, "teamRiftHeraldKills": 0, "tookLargeDamageSurvived": 0, "turretPlatesTaken": 1, "turretTakedowns": 0, "turretsTakenWithRiftHerald": 0, "twentyMinionsIn3SecondsCount": 0, "twoWardsOneSweeperCount": 0, "unseenRecalls": 0, "visionScoreAdvantageLaneOpponent": 0.7634588479995728, "visionScorePerMinute": 0.488436641471106, "voidMonsterKill": 0, "wardTakedowns": 1, "wardTakedownsBefore20M": 0, "wardsGuarded": 0}, "champExperience": 12304, "champLevel": 14, "championId": 202, "championName": "Jhin", "championTransform": 0, "commandPings": 4, "consumablesPurchased": 1, "damageDealtToBuildings": 662, "damageDealtToObjectives": 1920, "damageDealtToTurrets": 662, "damageSelfMitigated": 8376, "dangerPings": 0, "deaths": 4, "detectorWardsPlaced": 0, "doubleKills": 0, "dragonKills": 0, "eligibleForProgression": true, "enemyMissingPings": 4, "enemyVisionPings": 7, "firstBloodAssist": false, "firstBloodKill": false, "firstTowerAssist": false, "firstTowerKill": false, "gameEndedInEarlySurrender": false, "gameEndedInSurrender": false, "getBackPings": 3, "goldEarned": 10294, "goldSpent": 9350, "holdPings": 0, "individualPosition": "BOTTOM", "inhibitorKills": 0, "inhibitorTakedowns": 0, "inhibitorsLost": 3, "item0": 3009, "item1": 3087, "item2": 1055, "item3": 3031, "item4": 3086, "item5": 1042, "item6": 3340, "itemsPurchased": 16, "killingSprees": 1, "kills": 2, "lane": "BOTTOM", "largestCriticalStrike": 1139, "largestKillingSpree": 2, "largestMultiKill": 1, "longestTimeSpentLiving": 606, "magicDamageDealt": 29693, "magicDamageDealtToChampions": 1887, "magicDamageTaken": 15367, "missions": {"playerScore0": 0, "playerScore1": 0, "playerScore2": 0, "playerScore3": 0, "playerScore4": 0, "playerScore5": 0, "playerScore6": 0, "playerScore7": 0, "playerScore8": 0, "playerScore9": 0, "playerScore10": 0, "playerScore11": 0}, "needVisionPings": 1, "neutralMinionsKilled": 0, "nexusKills": 0, "nexusLost": 1, "nexusTakedowns": 0, "objectivesStolen": 0, "objectivesStolenAssists": 0, "onMyWayPings": 6, "participantId": 4, "pentaKills": 0, "perks": {"statPerks": {"defense": 5001, "flex": 5008, "offense": 5008}, "styles": [{"description": "primaryStyle", "selections": [{"perk": 8021, "var1": 1243, "var2": 1830, "var3": 0}, {"perk": 8009, "var1": 1564, "var2": 0, "var3": 0}, {"perk": 9103, "var1": 21, "var2": 50, "var3": 0}, {"perk": 8014, "var1": 244, "var2": 0, "var3": 0}], "style": 8000}, {"description": "subStyle", "selections": [{"perk": 8234, "var1": 10545, "var2": 0, "var3": 0}, {"perk": 8236, "var1": 14, "var2": 0, "var3": 0}], "style": 8200}]}, "physicalDamageDealt": 130810, "physicalDamageDealtToChampions": 16583, "physicalDamageTaken": 3335, "placement": 0, "playerAugment1": 0, "playerAugment2": 0, "playerAugment3": 0, "playerAugment4": 0, "playerAugment5": 0, "playerAugment6": 0, "playerSubteamId": 0, "profileIcon": 1641, "pushPings": 2, "puuid": "DP5AKk9T-2cXz-xyuelSuyjjelMbDnD7_SmCRSf0TCYzHl6lXbrYFrBli6bis3iwk7Amv3LSQ6hnLg", "quadraKills": 0, "riotIdGameName": "P0T3STAD3", "riotIdTagline": "BR1", "role": "CARRY", "sightWardsBoughtInGame": 0, "spell1Casts": 64, "spell2Casts": 37, "spell3Casts": 29, "spell4Casts": 23, "subteamPlacement": 0, "summoner1Casts": 3, "summoner1Id": 4, "summoner2Casts": 6, "summoner2Id": 21, "summonerId": "fP4B_MB1-VjywG-q-Jmaqe9DbeFFLhKyZKSEfz4z0SySMJc", "summonerLevel": 373, "summonerName": "P0T3STAD3", "teamEarlySurrendered": false, "teamId": 100, "teamPosition": "BOTTOM", "timeCCingOthers": 25, "timePlayed": 1722, "totalAllyJungleMinionsKilled": 0, "totalDamageDealt": 163931, "totalDamageDealtToChampions": 18688, "totalDamageShieldedOnTeammates": 0, "totalDamageTaken": 19218, "totalEnemyJungleMinionsKilled": 0, "totalHeal": 5189, "totalHealsOnTeammates": 0, "totalMinionsKilled": 231, "totalTimeCCDealt": 196, "totalTimeSpentDead": 73, "totalUnitsHealed": 1, "tripleKills": 0, "trueDamageDealt": 3427, "trueDamageDealtToChampions": 218, "trueDamageTaken": 516, "turretKills": 0, "turretTakedowns": 0, "turretsLost": 11, "unrealKills": 0, "visionClearedPings": 0, "visionScore": 14, "visionWardsBoughtInGame": 0, "wardsKilled": 1, "wardsPlaced": 8, "win": false}, {"allInPings": 0, "assistMePings": 0, "assists": 4, "baronKills": 0, "basicPings": 0, "bountyLevel": 0, "challenges": {"12AssistStreakCount": 0, "InfernalScalePickup": 16, "SWARM_DefeatAatrox": 0, "SWARM_DefeatBriar": 0, "SWARM_DefeatMiniBosses": 0, "SWARM_EvolveWeapon": 0, "SWARM_Have3Passives": 0, "SWARM_KillEnemy": 0, "SWARM_PickupGold": 0, "SWARM_ReachLevel50": 0, "SWARM_Survive15Min": 0, "SWARM_WinWith5EvolvedWeapons": 0, "abilityUses": 88, "acesBefore15Minutes": 0, "alliedJungleMonsterKills": 0, "baronTakedowns": 0, "blastConeOppositeOpponentCount": 0, "bountyGold": 675, "buffsStolen": 0, "completeSupportQuestInTime": 0, "controlWardsPlaced": 2, "damagePerMinute": 308.4377323217628, "damageTakenOnTeamPercentage": 0.1910820538544561, "dancedWithRiftHerald": 0, "deathsByEnemyChamps": 8, "dodgeSkillShotsSmallWindow": 25, "doubleAces": 0, "dragonTakedowns": 0, "earlyLaningPhaseGoldExpAdvantage": 0, "effectiveHealAndShielding": 2609.900390625, "elderDragonKillsWithOpposingSoul": 0, "elderDragonMultikills": 0, "enemyChampionImmobilizations": 62, "enemyJungleMonsterKills": 0, "epicMonsterKillsNearEnemyJungler": 0, "epicMonsterKillsWithin30SecondsOfSpawn": 0, "epicMonsterSteals": 0, "epicMonsterStolenWithoutSmite": 0, "firstTurretKilled": 0, "fistBumpParticipation": 1, "flawlessAces": 0, "fullTeamTakedown": 0, "gameLength": 1722.634910681, "getTakedownsInAllLanesEarlyJungleAsLaner": 0, "goldPerMinute": 251.77609505438704, "hadOpenNexus": 0, "highestWardKills": 1, "immobilizeAndKillWithAlly": 6, "initialBuffCount": 0, "initialCrabCount": 0, "jungleCsBefore10Minutes": 0, "junglerTakedownsNearDamagedEpicMonster": 0, "kTurretsDestroyedBeforePlatesFall": 0, "kda": 0.875, "killAfterHiddenWithAlly": 1, "killParticipation": 0.4117647058823529, "killedChampTookFullTeamDamageSurvived": 0, "killingSprees": 0, "killsNearEnemyTurret": 1, "killsOnOtherLanesEarlyJungleAsLaner": 0, "killsOnRecentlyHealedByAramPack": 0, "killsUnderOwnTurret": 0, "killsWithHelpFromEpicMonster": 1, "knockEnemyIntoTeamAndKill": 3, "landSkillShotsEarlyGame": 5, "laneMinionsFirst10Minutes": 7, "laningPhaseGoldExpAdvantage": 0, "legendaryCount": 0, "legendaryItemUsed": [3876, 3190, 3083], "lostAnInhibitor": 0, "maxCsAdvantageOnLaneOpponent": 3.5999999940395355, "maxKillDeficit": 0, "maxLevelLeadLaneOpponent": 1, "mejaisFullStackInTime": 0, "moreEnemyJungleThanOpponent": 0, "multiKillOneSpell": 0, "multiTurretRiftHeraldCount": 0, "multikills": 0, "multikillsAfterAggressiveFlash": 0, "outerTurretExecutesBefore10Minutes": 0, "outnumberedKills": 0, "outnumberedNexusKill": 0, "perfectDragonSoulsTaken": 0, "perfectGame": 0, "pickKillWithAlly": 7, "playedChampSelectPosition": 1, "poroExplosions": 0, "quickCleanse": 0, "quickFirstTurret": 0, "quickSoloKills": 0, "riftHeraldTakedowns": 0, "saveAllyFromDeath": 0, "scuttleCrabKills": 0, "skillshotsDodged": 153, "skillshotsHit": 19, "snowballsHit": 0, "soloBaronKills": 0, "soloKills": 0, "stealthWardsPlaced": 8, "survivedSingleDigitHpCount": 0, "survivedThreeImmobilizesInFight": 0, "takedownOnFirstTurret": 0, "takedowns": 7, "takedownsAfterGainingLevelAdvantage": 0, "takedownsBeforeJungleMinionSpawn": 0, "takedownsFirstXMinutes": 1, "takedownsInAlcove": 0, "takedownsInEnemyFountain": 0, "teamBaronKills": 0, "teamDamagePercentage": 0.11489217429808316, "teamElderDragonKills": 0, "teamRiftHeraldKills": 0, "tookLargeDamageSurvived": 0, "turretPlatesTaken": 1, "turretTakedowns": 0, "turretsTakenWithRiftHerald": 0, "twentyMinionsIn3SecondsCount": 0, "twoWardsOneSweeperCount": 1, "unseenRecalls": 0, "visionScoreAdvantageLaneOpponent": -0.5878149271011353, "visionScorePerMinute": 0.9368426929963836, "voidMonsterKill": 0, "wardTakedowns": 6, "wardTakedownsBefore20M": 2, "wardsGuarded": 0}, "champExperience": 9370, "champLevel": 12, "championId": 412, "championName": "Thresh", "championTransform": 0, "commandPings": 0, "consumablesPurchased": 4, "damageDealtToBuildings": 214, "damageDealtToObjectives": 320, "damageDealtToTurrets": 214, "damageSelfMitigated": 18393, "dangerPings": 0, "deaths": 8, "detectorWardsPlaced": 2, "doubleKills": 0, "dragonKills": 0, "eligibleForProgression": true, "enemyMissingPings": 0, "enemyVisionPings": 3, "firstBloodAssist": false, "firstBloodKill": false, "firstTowerAssist": false, "firstTowerKill": false, "gameEndedInEarlySurrender": false, "gameEndedInSurrender": false, "getBackPings": 0, "goldEarned": 7228, "goldSpent": 7200, "holdPings": 0, "individualPosition": "UTILITY", "inhibitorKills": 0, "inhibitorTakedowns": 0, "inhibitorsLost": 3, "item0": 3876, "item1": 3190, "item2": 3083, "item3": 3013, "item4": 0, "item5": 0, "item6": 3364, "itemsPurchased": 20, "killingSprees": 0, "kills": 3, "lane": "BOTTOM", "largestCriticalStrike": 0, "largestKillingSpree": 0, "largestMultiKill": 1, "longestTimeSpentLiving": 500, "magicDamageDealt": 11035, "magicDamageDealtToChampions": 6510, "magicDamageTaken": 20583, "missions": {"playerScore0": 0, "playerScore1": 0, "playerScore2": 0, "playerScore3": 0, "playerScore4": 0, "playerScore5": 0, "playerScore6": 0, "playerScore7": 0, "playerScore8": 0, "playerScore9": 0, "playerScore10": 0, "playerScore11": 0}, "needVisionPings": 0, "neutralMinionsKilled": 0, "nexusKills": 0, "nexusLost": 1, "nexusTakedowns": 0, "objectivesStolen": 0, "objectivesStolenAssists": 0, "onMyWayPings": 0, "participantId": 5, "pentaKills": 0, "perks": {"statPerks": {"defense": 5001, "flex": 5008, "offense": 5008}, "styles": [{"description": "primaryStyle", "selections": [{"perk": 8439, "var1": 282, "var2": 1070, "var3": 0}, {"perk": 8463, "var1": 753, "var2": 0, "var3": 0}, {"perk": 8444, "var1": 1599, "var2": 0, "var3": 0}, {"perk": 8451, "var1": 205, "var2": 0, "var3": 0}], "style": 8400}, {"description": "subStyle", "selections": [{"perk": 8345, "var1": 3, "var2": 0, "var3": 0}, {"perk": 8347, "var1": 0, "var2": 0, "var3": 0}], "style": 8300}]}, "physicalDamageDealt": 6107, "physicalDamageDealtToChampions": 1232, "physicalDamageTaken": 5427, "placement": 0, "playerAugment1": 0, "playerAugment2": 0, "playerAugment3": 0, "playerAugment4": 0, "playerAugment5": 0, "playerAugment6": 0, "playerSubteamId": 0, "profileIcon": 6499, "pushPings": 0, "puuid": "RUSb5mH-h0PAMtE8AeZZGL-bKlR8Y12e0PkTiMSpP33UrA79YVX9yJW-tZdmneMPz23Xb29r07ObHg", "quadraKills": 0, "riotIdGameName": "XAYAH LOL", "riotIdTagline": "bah", "role": "SUPPORT", "sightWardsBoughtInGame": 0, "spell1Casts": 36, "spell2Casts": 25, "spell3Casts": 21, "spell4Casts": 6, "subteamPlacement": 0, "summoner1Casts": 4, "summoner1Id": 4, "summoner2Casts": 7, "summoner2Id": 14, "summonerId": "JQNpyUdzsFuWcMY627OW8Z71UrqlDlboWpKN1AFYZCuXmQU", "summonerLevel": 457, "summonerName": "XAYAH LOL", "teamEarlySurrendered": false, "teamId": 100, "teamPosition": "UTILITY", "timeCCingOthers": 38, "timePlayed": 1722, "totalAllyJungleMinionsKilled": 0, "totalDamageDealt": 20950, "totalDamageDealtToChampions": 8855, "totalDamageShieldedOnTeammates": 2315, "totalDamageTaken": 26400, "totalEnemyJungleMinionsKilled": 0, "totalHeal": 660, "totalHealsOnTeammates": 294, "totalMinionsKilled": 23, "totalTimeCCDealt": 100, "totalTimeSpentDead": 164, "totalUnitsHealed": 5, "tripleKills": 0, "trueDamageDealt": 3806, "trueDamageDealtToChampions": 1112, "trueDamageTaken": 389, "turretKills": 0, "turretTakedowns": 0, "turretsLost": 11, "unrealKills": 0, "visionClearedPings": 0, "visionScore": 26, "visionWardsBoughtInGame": 2, "wardsKilled": 6, "wardsPlaced": 10, "win": false}, {"allInPings": 0, "assistMePings": 1, "assists": 12, "baronKills": 0, "basicPings": 0, "bountyLevel": 3, "challenges": {"12AssistStreakCount": 0, "InfernalScalePickup": 18, "SWARM_DefeatAatrox": 0, "SWARM_DefeatBriar": 0, "SWARM_DefeatMiniBosses": 0, "SWARM_EvolveWeapon": 0, "SWARM_Have3Passives": 0, "SWARM_KillEnemy": 0, "SWARM_PickupGold": 0, "SWARM_ReachLevel50": 0, "SWARM_Survive15Min": 0, "SWARM_WinWith5EvolvedWeapons": 0, "abilityUses": 275, "acesBefore15Minutes": 0, "alliedJungleMonsterKills": 0, "baronBuffGoldAdvantageOverThreshold": 1, "baronTakedowns": 1, "blastConeOppositeOpponentCount": 0, "bountyGold": 0, "buffsStolen": 0, "completeSupportQuestInTime": 0, "controlWardTimeCoverageInRiverOrEnemyHalf": 0.07899648820956695, "controlWardsPlaced": 1, "damagePerMinute": 808.7189295303219, "damageTakenOnTeamPercentage": 0.20203266525068703, "dancedWithRiftHerald": 0, "deathsByEnemyChamps": 2, "dodgeSkillShotsSmallWindow": 5, "doubleAces": 0, "dragonTakedowns": 0, "earliestBaron": 1578.1958925640001, "earlyLaningPhaseGoldExpAdvantage": 0, "effectiveHealAndShielding": 0, "elderDragonKillsWithOpposingSoul": 0, "elderDragonMultikills": 0, "enemyChampionImmobilizations": 40, "enemyJungleMonsterKills": 0, "epicMonsterKillsNearEnemyJungler": 0, "epicMonsterKillsWithin30SecondsOfSpawn": 0, "epicMonsterSteals": 0, "epicMonsterStolenWithoutSmite": 0, "firstTurretKilled": 1, "firstTurretKilledTime": 650.451080606, "fistBumpParticipation": 0, "flawlessAces": 0, "fullTeamTakedown": 1, "gameLength": 1722.634910681, "getTakedownsInAllLanesEarlyJungleAsLaner": 0, "goldPerMinute": 402.8375751645296, "hadOpenNexus": 0, "highestCrowdControlScore": 1, "immobilizeAndKillWithAlly": 6, "initialBuffCount": 0, "initialCrabCount": 0, "jungleCsBefore10Minutes": 0, "junglerTakedownsNearDamagedEpicMonster": 0, "kTurretsDestroyedBeforePlatesFall": 0, "kda": 8.5, "killAfterHiddenWithAlly": 1, "killParticipation": 0.4473684210526316, "killedChampTookFullTeamDamageSurvived": 0, "killingSprees": 1, "killsNearEnemyTurret": 1, "killsOnOtherLanesEarlyJungleAsLaner": 0, "killsOnRecentlyHealedByAramPack": 0, "killsUnderOwnTurret": 1, "killsWithHelpFromEpicMonster": 0, "knockEnemyIntoTeamAndKill": 4, "landSkillShotsEarlyGame": 14, "laneMinionsFirst10Minutes": 61, "laningPhaseGoldExpAdvantage": 0, "legendaryCount": 0, "legendaryItemUsed": [3116, 3118, 6653], "lostAnInhibitor": 0, "maxCsAdvantageOnLaneOpponent": 54, "maxKillDeficit": 0, "maxLevelLeadLaneOpponent": 3, "mejaisFullStackInTime": 0, "moreEnemyJungleThanOpponent": 0, "multiKillOneSpell": 0, "multiTurretRiftHeraldCount": 0, "multikills": 0, "multikillsAfterAggressiveFlash": 0, "outerTurretExecutesBefore10Minutes": 0, "outnumberedKills": 0, "outnumberedNexusKill": 0, "perfectDragonSoulsTaken": 1, "perfectGame": 0, "pickKillWithAlly": 12, "playedChampSelectPosition": 1, "poroExplosions": 0, "quickCleanse": 0, "quickFirstTurret": 0, "quickSoloKills": 0, "riftHeraldTakedowns": 1, "saveAllyFromDeath": 0, "scuttleCrabKills": 0, "skillshotsDodged": 38, "skillshotsHit": 46, "snowballsHit": 0, "soloBaronKills": 0, "soloKills": 2, "stealthWardsPlaced": 6, "survivedSingleDigitHpCount": 0, "survivedThreeImmobilizesInFight": 12, "takedownOnFirstTurret": 0, "takedowns": 17, "takedownsAfterGainingLevelAdvantage": 0, "takedownsBeforeJungleMinionSpawn": 1, "takedownsFirstXMinutes": 5, "takedownsInAlcove": 0, "takedownsInEnemyFountain": 0, "teamBaronKills": 1, "teamDamagePercentage": 0.19904726716270224, "teamElderDragonKills": 0, "teamRiftHeraldKills": 1, "teleportTakedowns": 2, "thirdInhibitorDestroyedTime": 1695.255115959, "tookLargeDamageSurvived": 0, "turretPlatesTaken": 2, "turretTakedowns": 4, "turretsTakenWithRiftHerald": 0, "twentyMinionsIn3SecondsCount": 0, "twoWardsOneSweeperCount": 0, "unseenRecalls": 0, "visionScoreAdvantageLaneOpponent": -0.03059709072113037, "visionScorePerMinute": 0.5294066031724031, "voidMonsterKill": 2, "wardTakedowns": 2, "wardTakedownsBefore20M": 2, "wardsGuarded": 1}, "champExperience": 16139, "champLevel": 16, "championId": 50, "championName": "Swain", "championTransform": 0, "commandPings": 2, "consumablesPurchased": 3, "damageDealtToBuildings": 4942, "damageDealtToObjectives": 8682, "damageDealtToTurrets": 4942, "damageSelfMitigated": 17133, "dangerPings": 0, "deaths": 2, "detectorWardsPlaced": 1, "doubleKills": 0, "dragonKills": 0, "eligibleForProgression": true, "enemyMissingPings": 13, "enemyVisionPings": 0, "firstBloodAssist": true, "firstBloodKill": false, "firstTowerAssist": false, "firstTowerKill": false, "gameEndedInEarlySurrender": false, "gameEndedInSurrender": false, "getBackPings": 0, "goldEarned": 11565, "goldSpent": 10925, "holdPings": 0, "individualPosition": "TOP", "inhibitorKills": 1, "inhibitorTakedowns": 2, "inhibitorsLost": 0, "item0": 3116, "item1": 3118, "item2": 3916, "item3": 6653, "item4": 3020, "item5": 0, "item6": 3364, "itemsPurchased": 19, "killingSprees": 2, "kills": 5, "lane": "MIDDLE", "largestCriticalStrike": 0, "largestKillingSpree": 3, "largestMultiKill": 1, "longestTimeSpentLiving": 1055, "magicDamageDealt": 124297, "magicDamageDealtToChampions": 20233, "magicDamageTaken": 8584, "missions": {"playerScore0": 0, "playerScore1": 0, "playerScore2": 0, "playerScore3": 0, "playerScore4": 0, "playerScore5": 0, "playerScore6": 0, "playerScore7": 0, "playerScore8": 0, "playerScore9": 0, "playerScore10": 0, "playerScore11": 0}, "needVisionPings": 0, "neutralMinionsKilled": 0, "nexusKills": 0, "nexusLost": 0, "nexusTakedowns": 1, "objectivesStolen": 0, "objectivesStolenAssists": 0, "onMyWayPings": 0, "participantId": 6, "pentaKills": 0, "perks": {"statPerks": {"defense": 5001, "flex": 5008, "offense": 5008}, "styles": [{"description": "primaryStyle", "selections": [{"perk": 8010, "var1": 170, "var2": 0, "var3": 0}, {"perk": 8009, "var1": 3563, "var2": 0, "var3": 0}, {"perk": 9105, "var1": 15, "var2": 20, "var3": 0}, {"perk": 8299, "var1": 402, "var2": 0, "var3": 0}], "style": 8000}, {"description": "subStyle", "selections": [{"perk": 8429, "var1": 58, "var2": 11, "var3": 10}, {"perk": 8451, "var1": 230, "var2": 0, "var3": 0}], "style": 8400}]}, "physicalDamageDealt": 19416, "physicalDamageDealtToChampions": 2685, "physicalDamageTaken": 15964, "placement": 0, "playerAugment1": 0, "playerAugment2": 0, "playerAugment3": 0, "playerAugment4": 0, "playerAugment5": 0, "playerAugment6": 0, "playerSubteamId": 0, "profileIcon": 508, "pushPings": 0, "puuid": "Oc3S3CKFvtVarGXpMUZbH7fXxr4lwkJsLUCtdmkWYLUSi89BRqPJAfWkLVC4iAJpMm9f1Tu71evQ5g", "quadraKills": 0, "riotIdGameName": "Alzheimerzinho", "riotIdTagline": "BR1", "role": "DUO", "sightWardsBoughtInGame": 0, "spell1Casts": 166, "spell2Casts": 32, "spell3Casts": 64, "spell4Casts": 13, "subteamPlacement": 0, "summoner1Casts": 5, "summoner1Id": 12, "summoner2Casts": 4, "summoner2Id": 4, "summonerId": "vW1kkM9EbEdcue9m8HajtF0pcG5MagK9X_tUL1F87hK9", "summonerLevel": 404, "summonerName": "Alzheimerzinho", "teamEarlySurrendered": false, "teamId": 200, "teamPosition": "TOP", "timeCCingOthers": 43, "timePlayed": 1722, "totalAllyJungleMinionsKilled": 0, "totalDamageDealt": 153588, "totalDamageDealtToChampions": 23218, "totalDamageShieldedOnTeammates": 0, "totalDamageTaken": 25035, "totalEnemyJungleMinionsKilled": 0, "totalHeal": 9999, "totalHealsOnTeammates": 0, "totalMinionsKilled": 179, "totalTimeCCDealt": 380, "totalTimeSpentDead": 57, "totalUnitsHealed": 1, "tripleKills": 0, "trueDamageDealt": 9874, "trueDamageDealtToChampions": 300, "trueDamageTaken": 487, "turretKills": 2, "turretTakedowns": 4, "turretsLost": 1, "unrealKills": 0, "visionClearedPings": 0, "visionScore": 15, "visionWardsBoughtInGame": 1, "wardsKilled": 2, "wardsPlaced": 7, "win": true}, {"allInPings": 1, "assistMePings": 4, "assists": 17, "baronKills": 1, "basicPings": 0, "bountyLevel": 3, "challenges": {"12AssistStreakCount": 0, "InfernalScalePickup": 13, "SWARM_DefeatAatrox": 0, "SWARM_DefeatBriar": 0, "SWARM_DefeatMiniBosses": 0, "SWARM_EvolveWeapon": 0, "SWARM_Have3Passives": 0, "SWARM_KillEnemy": 0, "SWARM_PickupGold": 0, "SWARM_ReachLevel50": 0, "SWARM_Survive15Min": 0, "SWARM_WinWith5EvolvedWeapons": 0, "abilityUses": 334, "acesBefore15Minutes": 0, "alliedJungleMonsterKills": 49, "baronBuffGoldAdvantageOverThreshold": 1, "baronTakedowns": 1, "blastConeOppositeOpponentCount": 0, "bountyGold": 0, "buffsStolen": 1, "completeSupportQuestInTime": 0, "controlWardTimeCoverageInRiverOrEnemyHalf": 0.7480629450993589, "controlWardsPlaced": 1, "damagePerMinute": 668.053513575059, "damageTakenOnTeamPercentage": 0.31687657335449104, "dancedWithRiftHerald": 0, "deathsByEnemyChamps": 3, "dodgeSkillShotsSmallWindow": 12, "doubleAces": 0, "dragonTakedowns": 4, "earliestBaron": 1578.1958925640001, "earliestDragonTakedown": 361.50804144200004, "earlyLaningPhaseGoldExpAdvantage": 1, "effectiveHealAndShielding": 263.2120361328125, "elderDragonKillsWithOpposingSoul": 0, "elderDragonMultikills": 0, "enemyChampionImmobilizations": 35, "enemyJungleMonsterKills": 17, "epicMonsterKillsNearEnemyJungler": 1, "epicMonsterKillsWithin30SecondsOfSpawn": 0, "epicMonsterSteals": 0, "epicMonsterStolenWithoutSmite": 0, "firstTurretKilled": 1, "firstTurretKilledTime": 650.451080606, "fistBumpParticipation": 0, "flawlessAces": 0, "fullTeamTakedown": 1, "gameLength": 1722.634910681, "goldPerMinute": 436.34356844965487, "hadOpenNexus": 0, "immobilizeAndKillWithAlly": 10, "initialBuffCount": 2, "initialCrabCount": 2, "jungleCsBefore10Minutes": 58.000000059604645, "junglerKillsEarlyJungle": 1, "junglerTakedownsNearDamagedEpicMonster": 0, "kTurretsDestroyedBeforePlatesFall": 0, "kda": 7, "killAfterHiddenWithAlly": 2, "killParticipation": 0.5526315789473685, "killedChampTookFullTeamDamageSurvived": 0, "killingSprees": 1, "killsNearEnemyTurret": 1, "killsOnLanersEarlyJungleAsJungler": 0, "killsOnRecentlyHealedByAramPack": 0, "killsUnderOwnTurret": 0, "killsWithHelpFromEpicMonster": 0, "knockEnemyIntoTeamAndKill": 0, "landSkillShotsEarlyGame": 0, "laneMinionsFirst10Minutes": 1, "laningPhaseGoldExpAdvantage": 0, "legendaryCount": 0, "legendaryItemUsed": [3050, 3083, 3109], "lostAnInhibitor": 0, "maxCsAdvantageOnLaneOpponent": 81.65000000596046, "maxKillDeficit": 0, "maxLevelLeadLaneOpponent": 4, "mejaisFullStackInTime": 0, "moreEnemyJungleThanOpponent": -38.60000005364418, "multiKillOneSpell": 0, "multiTurretRiftHeraldCount": 0, "multikills": 0, "multikillsAfterAggressiveFlash": 0, "outerTurretExecutesBefore10Minutes": 0, "outnumberedKills": 0, "outnumberedNexusKill": 0, "perfectDragonSoulsTaken": 1, "perfectGame": 0, "pickKillWithAlly": 18, "playedChampSelectPosition": 1, "poroExplosions": 0, "quickCleanse": 0, "quickFirstTurret": 0, "quickSoloKills": 0, "riftHeraldTakedowns": 1, "saveAllyFromDeath": 0, "scuttleCrabKills": 5, "skillshotsDodged": 78, "skillshotsHit": 9, "snowballsHit": 0, "soloBaronKills": 0, "soloKills": 1, "stealthWardsPlaced": 9, "survivedSingleDigitHpCount": 0, "survivedThreeImmobilizesInFight": 18, "takedownOnFirstTurret": 0, "takedowns": 21, "takedownsAfterGainingLevelAdvantage": 0, "takedownsBeforeJungleMinionSpawn": 1, "takedownsFirstXMinutes": 9, "takedownsInAlcove": 0, "takedownsInEnemyFountain": 0, "teamBaronKills": 1, "teamDamagePercentage": 0.1644257619551256, "teamElderDragonKills": 0, "teamRiftHeraldKills": 1, "thirdInhibitorDestroyedTime": 1695.255115959, "tookLargeDamageSurvived": 0, "turretPlatesTaken": 0, "turretTakedowns": 3, "turretsTakenWithRiftHerald": 0, "twentyMinionsIn3SecondsCount": 0, "twoWardsOneSweeperCount": 0, "unseenRecalls": 0, "visionScoreAdvantageLaneOpponent": 0.8479493856430054, "visionScorePerMinute": 1.1113681994165003, "voidMonsterKill": 5, "wardTakedowns": 4, "wardTakedownsBefore20M": 2, "wardsGuarded": 4}, "champExperience": 15630, "champLevel": 16, "championId": 113, "championName": "Sejuani", "championTransform": 0, "commandPings": 4, "consumablesPurchased": 2, "damageDealtToBuildings": 466, "damageDealtToObjectives": 36432, "damageDealtToTurrets": 466, "damageSelfMitigated": 62859, "dangerPings": 0, "deaths": 3, "detectorWardsPlaced": 1, "doubleKills": 0, "dragonKills": 4, "eligibleForProgression": true, "enemyMissingPings": 1, "enemyVisionPings": 0, "firstBloodAssist": true, "firstBloodKill": false, "firstTowerAssist": false, "firstTowerKill": false, "gameEndedInEarlySurrender": false, "gameEndedInSurrender": false, "getBackPings": 0, "goldEarned": 12527, "goldSpent": 11175, "holdPings": 0, "individualPosition": "JUNGLE", "inhibitorKills": 0, "inhibitorTakedowns": 2, "inhibitorsLost": 0, "item0": 3083, "item1": 3076, "item2": 3109, "item3": 3111, "item4": 3050, "item5": 1011, "item6": 3340, "itemsPurchased": 18, "killingSprees": 1, "kills": 4, "lane": "JUNGLE", "largestCriticalStrike": 4, "largestKillingSpree": 3, "largestMultiKill": 1, "longestTimeSpentLiving": 475, "magicDamageDealt": 46779, "magicDamageDealtToChampions": 7129, "magicDamageTaken": 12217, "missions": {"playerScore0": 0, "playerScore1": 0, "playerScore2": 0, "playerScore3": 0, "playerScore4": 0, "playerScore5": 0, "playerScore6": 0, "playerScore7": 0, "playerScore8": 0, "playerScore9": 0, "playerScore10": 0, "playerScore11": 0}, "needVisionPings": 0, "neutralMinionsKilled": 154, "nexusKills": 0, "nexusLost": 0, "nexusTakedowns": 1, "objectivesStolen": 0, "objectivesStolenAssists": 0, "onMyWayPings": 14, "participantId": 7, "pentaKills": 0, "perks": {"statPerks": {"defense": 5001, "flex": 5001, "offense": 5005}, "styles": [{"description": "primaryStyle", "selections": [{"perk": 8439, "var1": 402, "var2": 871, "var3": 0}, {"perk": 8463, "var1": 918, "var2": 0, "var3": 0}, {"perk": 8429, "var1": 58, "var2": 15, "var3": 11}, {"perk": 8451, "var1": 252, "var2": 0, "var3": 0}], "style": 8400}, {"description": "subStyle", "selections": [{"perk": 9104, "var1": 8, "var2": 50, "var3": 0}, {"perk": 9111, "var1": 1925, "var2": 420, "var3": 0}], "style": 8000}]}, "physicalDamageDealt": 102830, "physicalDamageDealtToChampions": 11380, "physicalDamageTaken": 25547, "placement": 0, "playerAugment1": 0, "playerAugment2": 0, "playerAugment3": 0, "playerAugment4": 0, "playerAugment5": 0, "playerAugment6": 0, "playerSubteamId": 0, "profileIcon": 6585, "pushPings": 0, "puuid": "HBkiEhOdgIONz6vvH24dcoDj7Inncl_6DEqqeo_zCrcdI1Suhtwdmji02YoI9ut7qC4wiRHQ9iGQ9w", "quadraKills": 0, "riotIdGameName": "Universo", "riotIdTagline": "AAD", "role": "NONE", "sightWardsBoughtInGame": 0, "spell1Casts": 67, "spell2Casts": 141, "spell3Casts": 118, "spell4Casts": 8, "subteamPlacement": 0, "summoner1Casts": 4, "summoner1Id": 4, "summoner2Casts": 18, "summoner2Id": 11, "summonerId": "sNlguodZPyB7dQ3ei7VV2sONyOcrc2pmplOD4TvBx06sTyc", "summonerLevel": 264, "summonerName": "Chad Bombado", "teamEarlySurrendered": false, "teamId": 200, "teamPosition": "JUNGLE", "timeCCingOthers": 37, "timePlayed": 1722, "totalAllyJungleMinionsKilled": 78, "totalDamageDealt": 243094, "totalDamageDealtToChampions": 19180, "totalDamageShieldedOnTeammates": 0, "totalDamageTaken": 39267, "totalEnemyJungleMinionsKilled": 21, "totalHeal": 15494, "totalHealsOnTeammates": 263, "totalMinionsKilled": 46, "totalTimeCCDealt": 497, "totalTimeSpentDead": 67, "totalUnitsHealed": 4, "tripleKills": 0, "trueDamageDealt": 93485, "trueDamageDealtToChampions": 670, "trueDamageTaken": 1502, "turretKills": 1, "turretTakedowns": 3, "turretsLost": 1, "unrealKills": 0, "visionClearedPings": 0, "visionScore": 31, "visionWardsBoughtInGame": 1, "wardsKilled": 4, "wardsPlaced": 11, "win": true}, {"allInPings": 0, "assistMePings": 6, "assists": 1, "baronKills": 0, "basicPings": 0, "bountyLevel": 0, "challenges": {"12AssistStreakCount": 0, "InfernalScalePickup": 14, "SWARM_DefeatAatrox": 0, "SWARM_DefeatBriar": 0, "SWARM_DefeatMiniBosses": 0, "SWARM_EvolveWeapon": 0, "SWARM_Have3Passives": 0, "SWARM_KillEnemy": 0, "SWARM_PickupGold": 0, "SWARM_ReachLevel50": 0, "SWARM_Survive15Min": 0, "SWARM_WinWith5EvolvedWeapons": 0, "abilityUses": 262, "acesBefore15Minutes": 0, "alliedJungleMonsterKills": 0, "baronBuffGoldAdvantageOverThreshold": 1, "baronTakedowns": 1, "blastConeOppositeOpponentCount": 0, "bountyGold": 0, "buffsStolen": 0, "completeSupportQuestInTime": 0, "controlWardTimeCoverageInRiverOrEnemyHalf": 0.7264075930559868, "controlWardsPlaced": 3, "damagePerMinute": 664.4966667937072, "damageTakenOnTeamPercentage": 0.186689523452872, "dancedWithRiftHerald": 0, "deathsByEnemyChamps": 4, "dodgeSkillShotsSmallWindow": 7, "doubleAces": 0, "dragonTakedowns": 3, "earliestBaron": 1578.1958925640001, "earliestDragonTakedown": 361.50804144200004, "earlyLaningPhaseGoldExpAdvantage": 1, "effectiveHealAndShielding": 0, "elderDragonKillsWithOpposingSoul": 0, "elderDragonMultikills": 0, "enemyChampionImmobilizations": 0, "enemyJungleMonsterKills": 0, "epicMonsterKillsNearEnemyJungler": 0, "epicMonsterKillsWithin30SecondsOfSpawn": 0, "epicMonsterSteals": 0, "epicMonsterStolenWithoutSmite": 0, "firstTurretKilled": 1, "firstTurretKilledTime": 650.451080606, "fistBumpParticipation": 0, "flawlessAces": 0, "fullTeamTakedown": 1, "gameLength": 1722.634910681, "getTakedownsInAllLanesEarlyJungleAsLaner": 0, "goldPerMinute": 405.9803011697223, "hadOpenNexus": 0, "immobilizeAndKillWithAlly": 0, "initialBuffCount": 0, "initialCrabCount": 0, "jungleCsBefore10Minutes": 0, "junglerTakedownsNearDamagedEpicMonster": 1, "kTurretsDestroyedBeforePlatesFall": 0, "kda": 3.5, "killAfterHiddenWithAlly": 2, "killParticipation": 0.3684210526315789, "killedChampTookFullTeamDamageSurvived": 0, "killingSprees": 3, "killsNearEnemyTurret": 3, "killsOnOtherLanesEarlyJungleAsLaner": 1, "killsOnRecentlyHealedByAramPack": 0, "killsUnderOwnTurret": 0, "killsWithHelpFromEpicMonster": 0, "knockEnemyIntoTeamAndKill": 0, "landSkillShotsEarlyGame": 8, "laneMinionsFirst10Minutes": 65, "laningPhaseGoldExpAdvantage": 0, "legendaryCount": 0, "legendaryItemUsed": [3100, 4645, 3135], "lostAnInhibitor": 0, "maxCsAdvantageOnLaneOpponent": 12, "maxKillDeficit": 0, "maxLevelLeadLaneOpponent": 2, "mejaisFullStackInTime": 0, "moreEnemyJungleThanOpponent": 0, "multiKillOneSpell": 0, "multiTurretRiftHeraldCount": 0, "multikills": 3, "multikillsAfterAggressiveFlash": 1, "outerTurretExecutesBefore10Minutes": 0, "outnumberedKills": 2, "outnumberedNexusKill": 0, "perfectDragonSoulsTaken": 1, "perfectGame": 0, "pickKillWithAlly": 10, "playedChampSelectPosition": 1, "poroExplosions": 0, "quickCleanse": 0, "quickFirstTurret": 0, "quickSoloKills": 0, "riftHeraldTakedowns": 0, "saveAllyFromDeath": 0, "scuttleCrabKills": 0, "skillshotsDodged": 56, "skillshotsHit": 37, "snowballsHit": 0, "soloBaronKills": 0, "soloKills": 4, "stealthWardsPlaced": 5, "survivedSingleDigitHpCount": 0, "survivedThreeImmobilizesInFight": 18, "takedownOnFirstTurret": 0, "takedowns": 14, "takedownsAfterGainingLevelAdvantage": 0, "takedownsBeforeJungleMinionSpawn": 1, "takedownsFirstXMinutes": 7, "takedownsInAlcove": 1, "takedownsInEnemyFountain": 0, "teamBaronKills": 1, "teamDamagePercentage": 0.1635503272327608, "teamElderDragonKills": 0, "teamRiftHeraldKills": 1, "thirdInhibitorDestroyedTime": 1695.255115959, "tookLargeDamageSurvived": 0, "turretPlatesTaken": 0, "turretTakedowns": 0, "turretsTakenWithRiftHerald": 0, "twentyMinionsIn3SecondsCount": 0, "twoWardsOneSweeperCount": 0, "unseenRecalls": 0, "visionScoreAdvantageLaneOpponent": 0.5092177391052246, "visionScorePerMinute": 1.1428917616817746, "voidMonsterKill": 1, "wardTakedowns": 1, "wardTakedownsBefore20M": 0, "wardsGuarded": 0}, "champExperience": 14243, "champLevel": 15, "championId": 84, "championName": "Akali", "championTransform": 0, "commandPings": 6, "consumablesPurchased": 4, "damageDealtToBuildings": 1608, "damageDealtToObjectives": 13367, "damageDealtToTurrets": 1608, "damageSelfMitigated": 12731, "dangerPings": 0, "deaths": 4, "detectorWardsPlaced": 3, "doubleKills": 3, "dragonKills": 0, "eligibleForProgression": true, "enemyMissingPings": 27, "enemyVisionPings": 17, "firstBloodAssist": false, "firstBloodKill": true, "firstTowerAssist": false, "firstTowerKill": false, "gameEndedInEarlySurrender": false, "gameEndedInSurrender": false, "getBackPings": 14, "goldEarned": 11655, "goldSpent": 11275, "holdPings": 0, "individualPosition": "MIDDLE", "inhibitorKills": 0, "inhibitorTakedowns": 0, "inhibitorsLost": 0, "item0": 3020, "item1": 2031, "item2": 0, "item3": 4645, "item4": 3135, "item5": 3100, "item6": 3363, "itemsPurchased": 23, "killingSprees": 3, "kills": 13, "lane": "MIDDLE", "largestCriticalStrike": 0, "largestKillingSpree": 6, "largestMultiKill": 2, "longestTimeSpentLiving": 686, "magicDamageDealt": 105872, "magicDamageDealtToChampions": 15408, "magicDamageTaken": 9315, "missions": {"playerScore0": 0, "playerScore1": 0, "playerScore2": 0, "playerScore3": 0, "playerScore4": 0, "playerScore5": 0, "playerScore6": 0, "playerScore7": 0, "playerScore8": 0, "playerScore9": 0, "playerScore10": 0, "playerScore11": 0}, "needVisionPings": 2, "neutralMinionsKilled": 0, "nexusKills": 0, "nexusLost": 0, "nexusTakedowns": 0, "objectivesStolen": 0, "objectivesStolenAssists": 0, "onMyWayPings": 27, "participantId": 8, "pentaKills": 0, "perks": {"statPerks": {"defense": 5001, "flex": 5008, "offense": 5008}, "styles": [{"description": "primaryStyle", "selections": [{"perk": 8112, "var1": 1038, "var2": 0, "var3": 0}, {"perk": 8143, "var1": 948, "var2": 0, "var3": 0}, {"perk": 8138, "var1": 30, "var2": 0, "var3": 0}, {"perk": 8106, "var1": 4, "var2": 0, "var3": 0}], "style": 8100}, {"description": "subStyle", "selections": [{"perk": 8444, "var1": 1011, "var2": 0, "var3": 0}, {"perk": 8451, "var1": 180, "var2": 0, "var3": 0}], "style": 8400}]}, "physicalDamageDealt": 12389, "physicalDamageDealtToChampions": 1296, "physicalDamageTaken": 13009, "placement": 0, "playerAugment1": 0, "playerAugment2": 0, "playerAugment3": 0, "playerAugment4": 0, "playerAugment5": 0, "playerAugment6": 0, "playerSubteamId": 0, "profileIcon": 6049, "pushPings": 0, "puuid": "y_jizTOkVdva02Q545jf0onoHKHdcXiQ1u3GjMtlRGag6foBj7paNPCqF9Iu7ZTwCt6m0mEyVmRwdA", "quadraKills": 0, "riotIdGameName": "Sir Reset", "riotIdTagline": "RESET", "role": "DUO", "sightWardsBoughtInGame": 0, "spell1Casts": 151, "spell2Casts": 32, "spell3Casts": 64, "spell4Casts": 15, "subteamPlacement": 0, "summoner1Casts": 6, "summoner1Id": 14, "summoner2Casts": 4, "summoner2Id": 4, "summonerId": "W5lfwwWWUOWlIUtkP-nst75SEiztb590AEvHymwaCNKyFME", "summonerLevel": 548, "summonerName": "Sir Reset", "teamEarlySurrendered": false, "teamId": 200, "teamPosition": "MIDDLE", "timeCCingOthers": 2, "timePlayed": 1722, "totalAllyJungleMinionsKilled": 0, "totalDamageDealt": 125995, "totalDamageDealtToChampions": 19078, "totalDamageShieldedOnTeammates": 0, "totalDamageTaken": 23134, "totalEnemyJungleMinionsKilled": 0, "totalHeal": 1868, "totalHealsOnTeammates": 0, "totalMinionsKilled": 162, "totalTimeCCDealt": 79, "totalTimeSpentDead": 155, "totalUnitsHealed": 1, "tripleKills": 0, "trueDamageDealt": 7733, "trueDamageDealtToChampions": 2372, "trueDamageTaken": 810, "turretKills": 0, "turretTakedowns": 0, "turretsLost": 1, "unrealKills": 0, "visionClearedPings": 0, "visionScore": 32, "visionWardsBoughtInGame": 3, "wardsKilled": 1, "wardsPlaced": 12, "win": true}, {"allInPings": 0, "assistMePings": 1, "assists": 13, "baronKills": 0, "basicPings": 0, "bountyLevel": 7, "challenges": {"12AssistStreakCount": 0, "InfernalScalePickup": 7, "SWARM_DefeatAatrox": 0, "SWARM_DefeatBriar": 0, "SWARM_DefeatMiniBosses": 0, "SWARM_EvolveWeapon": 0, "SWARM_Have3Passives": 0, "SWARM_KillEnemy": 0, "SWARM_PickupGold": 0, "SWARM_ReachLevel50": 0, "SWARM_Survive15Min": 0, "SWARM_WinWith5EvolvedWeapons": 0, "abilityUses": 290, "acesBefore15Minutes": 0, "alliedJungleMonsterKills": 0, "baronBuffGoldAdvantageOverThreshold": 1, "baronTakedowns": 0, "blastConeOppositeOpponentCount": 0, "bountyGold": 0, "buffsStolen": 1, "completeSupportQuestInTime": 0, "controlWardsPlaced": 0, "damagePerMinute": 1428.5670840591208, "damageTakenOnTeamPercentage": 0.13027879542120352, "dancedWithRiftHerald": 0, "deathsByEnemyChamps": 1, "dodgeSkillShotsSmallWindow": 2, "doubleAces": 0, "dragonTakedowns": 3, "earliestBaron": 1578.1958925640001, "earliestDragonTakedown": 692.0343825760001, "earlyLaningPhaseGoldExpAdvantage": 0, "effectiveHealAndShielding": 0, "elderDragonKillsWithOpposingSoul": 0, "elderDragonMultikills": 0, "enemyChampionImmobilizations": 16, "enemyJungleMonsterKills": 2, "epicMonsterKillsNearEnemyJungler": 0, "epicMonsterKillsWithin30SecondsOfSpawn": 0, "epicMonsterSteals": 0, "epicMonsterStolenWithoutSmite": 0, "firstTurretKilled": 1, "firstTurretKilledTime": 650.451080606, "fistBumpParticipation": 0, "flawlessAces": 0, "fullTeamTakedown": 1, "gameLength": 1722.634910681, "getTakedownsInAllLanesEarlyJungleAsLaner": 0, "goldPerMinute": 517.0863033401629, "hadOpenNexus": 0, "highestChampionDamage": 1, "immobilizeAndKillWithAlly": 6, "initialBuffCount": 0, "initialCrabCount": 0, "jungleCsBefore10Minutes": 0, "junglerTakedownsNearDamagedEpicMonster": 1, "kTurretsDestroyedBeforePlatesFall": 1, "kda": 24, "killAfterHiddenWithAlly": 2, "killParticipation": 0.631578947368421, "killedChampTookFullTeamDamageSurvived": 0, "killingSprees": 2, "killsNearEnemyTurret": 7, "killsOnOtherLanesEarlyJungleAsLaner": 0, "killsOnRecentlyHealedByAramPack": 0, "killsUnderOwnTurret": 0, "killsWithHelpFromEpicMonster": 0, "knockEnemyIntoTeamAndKill": 6, "landSkillShotsEarlyGame": 15, "laneMinionsFirst10Minutes": 63, "laningPhaseGoldExpAdvantage": 1, "legendaryCount": 0, "legendaryItemUsed": [6655, 6653, 3135], "lostAnInhibitor": 0, "maxCsAdvantageOnLaneOpponent": 18, "maxKillDeficit": 0, "maxLevelLeadLaneOpponent": 2, "mejaisFullStackInTime": 0, "moreEnemyJungleThanOpponent": 0, "multiKillOneSpell": 0, "multiTurretRiftHeraldCount": 0, "multikills": 1, "multikillsAfterAggressiveFlash": 0, "outerTurretExecutesBefore10Minutes": 0, "outnumberedKills": 0, "outnumberedNexusKill": 0, "perfectDragonSoulsTaken": 1, "perfectGame": 0, "pickKillWithAlly": 21, "playedChampSelectPosition": 1, "poroExplosions": 0, "quickCleanse": 0, "quickFirstTurret": 0, "quickSoloKills": 0, "riftHeraldTakedowns": 0, "saveAllyFromDeath": 0, "scuttleCrabKills": 0, "skillshotsDodged": 21, "skillshotsHit": 108, "snowballsHit": 0, "soloBaronKills": 0, "soloKills": 1, "stealthWardsPlaced": 4, "survivedSingleDigitHpCount": 0, "survivedThreeImmobilizesInFight": 12, "takedownOnFirstTurret": 1, "takedowns": 24, "takedownsAfterGainingLevelAdvantage": 0, "takedownsBeforeJungleMinionSpawn": 1, "takedownsFirstXMinutes": 8, "takedownsInAlcove": 0, "takedownsInEnemyFountain": 0, "teamBaronKills": 1, "teamDamagePercentage": 0.351608406403571, "teamElderDragonKills": 0, "teamRiftHeraldKills": 1, "thirdInhibitorDestroyedTime": 1695.255115959, "tookLargeDamageSurvived": 0, "turretPlatesTaken": 5, "turretTakedowns": 6, "turretsTakenWithRiftHerald": 0, "twentyMinionsIn3SecondsCount": 0, "twoWardsOneSweeperCount": 0, "unseenRecalls": 0, "visionScoreAdvantageLaneOpponent": -0.43293261528015137, "visionScorePerMinute": 0.2769764858794432, "voidMonsterKill": 0, "wardTakedowns": 1, "wardTakedownsBefore20M": 0, "wardsGuarded": 0}, "champExperience": 14941, "champLevel": 16, "championId": 115, "championName": "Ziggs", "championTransform": 0, "commandPings": 0, "consumablesPurchased": 2, "damageDealtToBuildings": 12020, "damageDealtToObjectives": 20138, "damageDealtToTurrets": 12020, "damageSelfMitigated": 8504, "dangerPings": 0, "deaths": 1, "detectorWardsPlaced": 0, "doubleKills": 1, "dragonKills": 0, "eligibleForProgression": true, "enemyMissingPings": 0, "enemyVisionPings": 3, "firstBloodAssist": true, "firstBloodKill": false, "firstTowerAssist": false, "firstTowerKill": true, "gameEndedInEarlySurrender": false, "gameEndedInSurrender": false, "getBackPings": 3, "goldEarned": 14845, "goldSpent": 11900, "holdPings": 0, "individualPosition": "BOTTOM", "inhibitorKills": 2, "inhibitorTakedowns": 2, "inhibitorsLost": 0, "item0": 3135, "item1": 3916, "item2": 3108, "item3": 6655, "item4": 3020, "item5": 6653, "item6": 3340, "itemsPurchased": 17, "killingSprees": 2, "kills": 11, "lane": "BOTTOM", "largestCriticalStrike": 0, "largestKillingSpree": 7, "largestMultiKill": 2, "longestTimeSpentLiving": 1105, "magicDamageDealt": 175264, "magicDamageDealtToChampions": 39677, "magicDamageTaken": 5412, "missions": {"playerScore0": 0, "playerScore1": 0, "playerScore2": 0, "playerScore3": 0, "playerScore4": 0, "playerScore5": 0, "playerScore6": 0, "playerScore7": 0, "playerScore8": 0, "playerScore9": 0, "playerScore10": 0, "playerScore11": 0}, "needVisionPings": 0, "neutralMinionsKilled": 5, "nexusKills": 0, "nexusLost": 0, "nexusTakedowns": 1, "objectivesStolen": 0, "objectivesStolenAssists": 0, "onMyWayPings": 9, "participantId": 9, "pentaKills": 0, "perks": {"statPerks": {"defense": 5001, "flex": 5008, "offense": 5008}, "styles": [{"description": "primaryStyle", "selections": [{"perk": 8229, "var1": 1929, "var2": 0, "var3": 0}, {"perk": 8226, "var1": 250, "var2": 1161, "var3": 0}, {"perk": 8210, "var1": 22, "var2": 0, "var3": 0}, {"perk": 8237, "var1": 803, "var2": 0, "var3": 0}], "style": 8200}, {"description": "subStyle", "selections": [{"perk": 8345, "var1": 3, "var2": 0, "var3": 0}, {"perk": 8304, "var1": 8, "var2": 1, "var3": 5}], "style": 8300}]}, "physicalDamageDealt": 13282, "physicalDamageDealtToChampions": 1273, "physicalDamageTaken": 10034, "placement": 0, "playerAugment1": 0, "playerAugment2": 0, "playerAugment3": 0, "playerAugment4": 0, "playerAugment5": 0, "playerAugment6": 0, "playerSubteamId": 0, "profileIcon": 6382, "pushPings": 0, "puuid": "rDib1FSxplhn5DSdcgixAI39obnCHkf85klzk5Nyakk0nrG7QxfhtB9ZkRy00vNby7k1gSeN8sXfqw", "quadraKills": 0, "riotIdGameName": "Bald\u00e3o", "riotIdTagline": "111", "role": "CARRY", "sightWardsBoughtInGame": 0, "spell1Casts": 181, "spell2Casts": 48, "spell3Casts": 48, "spell4Casts": 13, "subteamPlacement": 0, "summoner1Casts": 2, "summoner1Id": 12, "summoner2Casts": 4, "summoner2Id": 4, "summonerId": "MAkAQ2wmuVI0Hk8nPfFwhbixNZ8SkbersS4wSMVZa9JJ", "summonerLevel": 462, "summonerName": "ti\u00e3o trompete", "teamEarlySurrendered": false, "teamId": 200, "teamPosition": "BOTTOM", "timeCCingOthers": 19, "timePlayed": 1722, "totalAllyJungleMinionsKilled": 0, "totalDamageDealt": 194875, "totalDamageDealtToChampions": 41014, "totalDamageShieldedOnTeammates": 0, "totalDamageTaken": 16144, "totalEnemyJungleMinionsKilled": 5, "totalHeal": 2580, "totalHealsOnTeammates": 0, "totalMinionsKilled": 209, "totalTimeCCDealt": 270, "totalTimeSpentDead": 36, "totalUnitsHealed": 1, "tripleKills": 0, "trueDamageDealt": 6329, "trueDamageDealtToChampions": 63, "trueDamageTaken": 697, "turretKills": 5, "turretTakedowns": 6, "turretsLost": 1, "unrealKills": 0, "visionClearedPings": 0, "visionScore": 7, "visionWardsBoughtInGame": 0, "wardsKilled": 1, "wardsPlaced": 4, "win": true}, {"allInPings": 0, "assistMePings": 1, "assists": 18, "baronKills": 0, "basicPings": 0, "bountyLevel": 1, "challenges": {"12AssistStreakCount": 0, "InfernalScalePickup": 18, "SWARM_DefeatAatrox": 0, "SWARM_DefeatBriar": 0, "SWARM_DefeatMiniBosses": 0, "SWARM_EvolveWeapon": 0, "SWARM_Have3Passives": 0, "SWARM_KillEnemy": 0, "SWARM_PickupGold": 0, "SWARM_ReachLevel50": 0, "SWARM_Survive15Min": 0, "SWARM_WinWith5EvolvedWeapons": 0, "abilityUses": 308, "acesBefore15Minutes": 0, "alliedJungleMonsterKills": 0, "baronBuffGoldAdvantageOverThreshold": 1, "baronTakedowns": 1, "blastConeOppositeOpponentCount": 0, "bountyGold": 0, "buffsStolen": 0, "completeSupportQuestInTime": 1, "controlWardTimeCoverageInRiverOrEnemyHalf": 0.8311344031614902, "controlWardsPlaced": 2, "damagePerMinute": 493.11297916091235, "damageTakenOnTeamPercentage": 0.16412244252074637, "dancedWithRiftHerald": 0, "deathsByEnemyChamps": 7, "dodgeSkillShotsSmallWindow": 3, "doubleAces": 0, "dragonTakedowns": 4, "earliestBaron": 1578.1958925640001, "earliestDragonTakedown": 361.50804144200004, "earlyLaningPhaseGoldExpAdvantage": 0, "effectiveHealAndShielding": 8464.26953125, "elderDragonKillsWithOpposingSoul": 0, "elderDragonMultikills": 0, "enemyChampionImmobilizations": 16, "enemyJungleMonsterKills": 2, "epicMonsterKillsNearEnemyJungler": 0, "epicMonsterKillsWithin30SecondsOfSpawn": 0, "epicMonsterSteals": 0, "epicMonsterStolenWithoutSmite": 0, "fasterSupportQuestCompletion": 1, "firstTurretKilled": 1, "firstTurretKilledTime": 650.451080606, "fistBumpParticipation": 0, "flawlessAces": 0, "fullTeamTakedown": 1, "gameLength": 1722.634910681, "getTakedownsInAllLanesEarlyJungleAsLaner": 0, "goldPerMinute": 340.86354215814185, "hadOpenNexus": 0, "immobilizeAndKillWithAlly": 6, "initialBuffCount": 0, "initialCrabCount": 0, "jungleCsBefore10Minutes": 0, "junglerTakedownsNearDamagedEpicMonster": 1, "kTurretsDestroyedBeforePlatesFall": 1, "kda": 3.2857142857142856, "killAfterHiddenWithAlly": 2, "killParticipation": 0.6052631578947368, "killedChampTookFullTeamDamageSurvived": 0, "killingSprees": 1, "killsNearEnemyTurret": 4, "killsOnOtherLanesEarlyJungleAsLaner": 0, "killsOnRecentlyHealedByAramPack": 0, "killsUnderOwnTurret": 0, "killsWithHelpFromEpicMonster": 0, "knockEnemyIntoTeamAndKill": 0, "landSkillShotsEarlyGame": 13, "laneMinionsFirst10Minutes": 9, "laningPhaseGoldExpAdvantage": 0, "legendaryCount": 0, "legendaryItemUsed": [6620, 3870, 6617, 3165], "lostAnInhibitor": 0, "maxCsAdvantageOnLaneOpponent": 4.4000000059604645, "maxKillDeficit": 0, "maxLevelLeadLaneOpponent": 1, "mejaisFullStackInTime": 0, "moreEnemyJungleThanOpponent": 0, "multiKillOneSpell": 0, "multiTurretRiftHeraldCount": 0, "multikills": 1, "multikillsAfterAggressiveFlash": 0, "outerTurretExecutesBefore10Minutes": 0, "outnumberedKills": 0, "outnumberedNexusKill": 0, "perfectDragonSoulsTaken": 1, "perfectGame": 0, "pickKillWithAlly": 20, "playedChampSelectPosition": 1, "poroExplosions": 0, "quickCleanse": 0, "quickFirstTurret": 0, "quickSoloKills": 0, "riftHeraldTakedowns": 1, "saveAllyFromDeath": 1, "scuttleCrabKills": 1, "skillshotsDodged": 28, "skillshotsHit": 41, "snowballsHit": 0, "soloBaronKills": 0, "soloKills": 0, "stealthWardsPlaced": 20, "survivedSingleDigitHpCount": 0, "survivedThreeImmobilizesInFight": 6, "takedownOnFirstTurret": 1, "takedowns": 23, "takedownsAfterGainingLevelAdvantage": 0, "takedownsBeforeJungleMinionSpawn": 1, "takedownsFirstXMinutes": 8, "takedownsInAlcove": 0, "takedownsInEnemyFountain": 0, "teamBaronKills": 1, "teamDamagePercentage": 0.12136823724584034, "teamElderDragonKills": 0, "teamRiftHeraldKills": 1, "thirdInhibitorDestroyedTime": 1695.255115959, "tookLargeDamageSurvived": 0, "turretPlatesTaken": 5, "turretTakedowns": 4, "turretsTakenWithRiftHerald": 0, "twentyMinionsIn3SecondsCount": 0, "twoWardsOneSweeperCount": 0, "unseenRecalls": 0, "visionScoreAdvantageLaneOpponent": 1.4260942935943604, "visionScorePerMinute": 2.272868822567006, "voidMonsterKill": 2, "wardTakedowns": 2, "wardTakedownsBefore20M": 1, "wardsGuarded": 1}, "champExperience": 10186, "champLevel": 13, "championId": 43, "championName": "Karma", "championTransform": 0, "commandPings": 10, "consumablesPurchased": 5, "damageDealtToBuildings": 942, "damageDealtToObjectives": 11954, "damageDealtToTurrets": 942, "damageSelfMitigated": 10155, "dangerPings": 0, "deaths": 7, "detectorWardsPlaced": 2, "doubleKills": 1, "dragonKills": 0, "eligibleForProgression": true, "enemyMissingPings": 9, "enemyVisionPings": 4, "firstBloodAssist": true, "firstBloodKill": false, "firstTowerAssist": true, "firstTowerKill": false, "gameEndedInEarlySurrender": false, "gameEndedInSurrender": false, "getBackPings": 0, "goldEarned": 9786, "goldSpent": 8325, "holdPings": 0, "individualPosition": "UTILITY", "inhibitorKills": 0, "inhibitorTakedowns": 1, "inhibitorsLost": 0, "item0": 3870, "item1": 2055, "item2": 6620, "item3": 3158, "item4": 6617, "item5": 3165, "item6": 3364, "itemsPurchased": 21, "killingSprees": 1, "kills": 5, "lane": "BOTTOM", "largestCriticalStrike": 0, "largestKillingSpree": 3, "largestMultiKill": 2, "longestTimeSpentLiving": 270, "magicDamageDealt": 26642, "magicDamageDealtToChampions": 12122, "magicDamageTaken": 7644, "missions": {"playerScore0": 0, "playerScore1": 0, "playerScore2": 0, "playerScore3": 0, "playerScore4": 0, "playerScore5": 0, "playerScore6": 0, "playerScore7": 0, "playerScore8": 0, "playerScore9": 0, "playerScore10": 0, "playerScore11": 0}, "needVisionPings": 0, "neutralMinionsKilled": 5, "nexusKills": 1, "nexusLost": 0, "nexusTakedowns": 1, "objectivesStolen": 0, "objectivesStolenAssists": 0, "onMyWayPings": 13, "participantId": 10, "pentaKills": 0, "perks": {"statPerks": {"defense": 5011, "flex": 5008, "offense": 5007}, "styles": [{"description": "primaryStyle", "selections": [{"perk": 8214, "var1": 953, "var2": 356, "var3": 0}, {"perk": 8226, "var1": 250, "var2": 272, "var3": 0}, {"perk": 8210, "var1": 4, "var2": 0, "var3": 0}, {"perk": 8237, "var1": 550, "var2": 0, "var3": 0}], "style": 8200}, {"description": "subStyle", "selections": [{"perk": 8463, "var1": 721, "var2": 0, "var3": 0}, {"perk": 8453, "var1": 737, "var2": 1550, "var3": 0}], "style": 8400}]}, "physicalDamageDealt": 6262, "physicalDamageDealtToChampions": 1335, "physicalDamageTaken": 11737, "placement": 0, "playerAugment1": 0, "playerAugment2": 0, "playerAugment3": 0, "playerAugment4": 0, "playerAugment5": 0, "playerAugment6": 0, "playerSubteamId": 0, "profileIcon": 5980, "pushPings": 0, "puuid": "jMs2_SjqNWHe9uAp-hfp541qqXOmeYNQ5khxyOqT_PPmRmveXvtl7miQKwX90ZYl5ZE9jPb-mspBrA", "quadraKills": 0, "riotIdGameName": "MattShadz", "riotIdTagline": "BR1", "role": "SUPPORT", "sightWardsBoughtInGame": 0, "spell1Casts": 93, "spell2Casts": 38, "spell3Casts": 134, "spell4Casts": 43, "subteamPlacement": 0, "summoner1Casts": 5, "summoner1Id": 4, "summoner2Casts": 7, "summoner2Id": 14, "summonerId": "VHou2cjX880fIVgM4u0w2dFamjdcvFnwNGiRd06YERyxOw", "summonerLevel": 538, "summonerName": "MattShadz", "teamEarlySurrendered": false, "teamId": 200, "teamPosition": "UTILITY", "timeCCingOthers": 32, "timePlayed": 1722, "totalAllyJungleMinionsKilled": 0, "totalDamageDealt": 39037, "totalDamageDealtToChampions": 14157, "totalDamageShieldedOnTeammates": 4169, "totalDamageTaken": 20338, "totalEnemyJungleMinionsKilled": 1, "totalHeal": 7020, "totalHealsOnTeammates": 4295, "totalMinionsKilled": 18, "totalTimeCCDealt": 166, "totalTimeSpentDead": 143, "totalUnitsHealed": 5, "tripleKills": 0, "trueDamageDealt": 6132, "trueDamageDealtToChampions": 700, "trueDamageTaken": 955, "turretKills": 1, "turretTakedowns": 4, "turretsLost": 1, "unrealKills": 0, "visionClearedPings": 0, "visionScore": 65, "visionWardsBoughtInGame": 3, "wardsKilled": 2, "wardsPlaced": 23, "win": true}], "platformId": "BR1", "queueId": 420, "teams": [{"bans": [{"championId": 25, "pickTurn": 1}, {"championId": 55, "pickTurn": 2}, {"championId": 75, "pickTurn": 3}, {"championId": 221, "pickTurn": 4}, {"championId": -1, "pickTurn": 5}], "objectives": {"baron": {"first": false, "kills": 0}, "champion": {"first": false, "kills": 17}, "dragon": {"first": false, "kills": 0}, "horde": {"first": false, "kills": 0}, "inhibitor": {"first": false, "kills": 0}, "riftHerald": {"first": false, "kills": 0}, "tower": {"first": false, "kills": 1}}, "teamId": 100, "win": false}, {"bans": [{"championId": 360, "pickTurn": 6}, {"championId": 99, "pickTurn": 7}, {"championId": 7, "pickTurn": 8}, {"championId": -1, "pickTurn": 9}, {"championId": 82, "pickTurn": 10}], "objectives": {"baron": {"first": true, "kills": 1}, "champion": {"first": true, "kills": 38}, "dragon": {"first": true, "kills": 4}, "horde": {"first": true, "kills": 3}, "inhibitor": {"first": true, "kills": 3}, "riftHerald": {"first": true, "kills": 1}, "tower": {"first": true, "kills": 11}}, "teamId": 200, "win": true}], "tournamentCode": ""}}